<!--
This file is used by tc2dracor.xq. It maps DraCor IDs for FreDraCor to the file
names of the plays in theatre-classique.fr and adds Wikidata IDs where available.
-->
<ids>
  <play id="fre000001" file="ABEILLE_ARGELIE.xml" wikidata="Q63215430"/>
  <play id="fre000002" file="ABEILLE_CORIOLAN.xml" wikidata="Q63214898"/>
  <play id="fre000003" file="ABEILLE_LYNCEE.xml" wikidata="Q63215163"/>
  <play id="fre000004" file="ADENIS_HOMMEQUINEPEUTPASSIFFLER.xml"/>
  <play id="fre000005" file="AIGUEBERRE_AVAREAMOUREUX.xml"/>
  <play id="fre000006" file="AIGUEBERRE_PANETDORIS.xml"/>
  <play id="fre000007" file="AIGUEBERRE_POLIXENE.xml"/>
  <play id="fre000008" file="AIGUEBERRE_PROLOGUE.xml"/>
  <play id="fre000009" file="ALAINLEGRAND_EPREUVERECIPROQUE.xml"/>
  <play id="fre000010" file="ALLAINVAL_ECOLEDESBOURGEOIS.xml"/>
  <play id="fre000011" file="ALLAINVAL_HIVER.xml"/>
  <play id="fre000012" file="ALLAIS_BONBOUGRE.xml"/>
  <play id="fre000013" file="ALLAIS_MECONTENT.xml"/>
  <play id="fre000014" file="ANCELOT-ARAGO_PAPILLOTES.xml"/>
  <play id="fre000015" file="ANDRIEUX_ANAXIMANDRE.xml"/>
  <play id="fre000016" file="ANDRIEUX_MOLIEREETSESAMIS.xml"/>
  <play id="fre000017" file="ANONYME_ADAM.xml" slug="anonyme-adam" written="1150–1170" wikidata="Q1008497"/>
  <play id="fre000018" file="ANONYME_AVENTURESDENINETTE.xml"/>
  <play id="fre000019" file="ANONYME_BONNESGENS.xml"/>
  <play id="fre000020" file="ANONYME_CHAPELAINDECOIFFE.xml"/>
  <play id="fre000021" file="ANONYME_CHAPELAINDECOIFFE_2.xml"/>
  <play id="fre000022" file="ANONYME_CLUBDESDAMES.xml"/>
  <play id="fre000023" file="ANONYME_DEROUTEDESPRECIEUSES.xml"/>
  <play id="fre000024" file="ANONYME_DIALOGUEROUSSEAUVOLTAIRE.xml"/>
  <play id="fre000025" file="ANONYME_JEUDESMOREE.xml"/>
  <play id="fre000026" file="ANONYME_JUSDUPELERIN.xml"/>
  <play id="fre000027" file="ANONYME_MATINEECOMEDIENFRANCAIS.xml"/>
  <play id="fre000028" file="ANONYME_PARDONNEUR.xml" slug="anonyme-farce-nouvelle-tres-bonne-et-fort-joyeuse-a-trois-personnages" written="1517–1520"/>
  <play id="fre000029" file="ANONYME_PONTAUXANES.xml" slug="anonyme-farce-nouvelle-fort-joyeuse-du-pont-aux-anes" written="1480"/>
  <play id="fre000030" file="ANONYME_PORTIERDUPARNASSE.xml"/>
  <play id="fre000031" file="ANONYME_PRIXDUNMOMENT.xml"/>
  <play id="fre000032" file="ANONYME_RECEPTIONARGENSON.xml"/>
  <play id="fre000033" file="ANONYME_RESURRECTIONDUSAUVEUR.xml"/>
  <play id="fre000034" file="ANONYME_RESURRECTIONJENINLANDORE.xml" slug="anonyme-farce-nouvelle-tres-bonne-et-fort-joyeuse-de-la-resurrection-de-jenin-landore" written="1511–1512" print="1547–1557"/>
  <play id="fre000035" file="ANONYME_SAUVAGESCIVILISES.xml"/>
  <play id="fre000036" file="ANONYME_SERAILDEDELYS.xml"/>
  <play id="fre000037" file="ANONYME_SERMONJOYEUX.xml" slug="anonyme-sermon-joyeux-de-bien-boire" print="1545"/>
  <play id="fre000038" file="ANONYME_VENDE.xml"/>
  <play id="fre000039" file="ANONYME_VIERGESFOLLESVIERGESSAGES.xml"/>
  <play id="fre000040" file="ANONYME_VOILABIENLEDIABLE.xml"/>
  <play id="fre000041" file="ANONYME_ZELAMIRE.xml"/>
  <play id="fre000042" file="ANSEAUME_CENDRILLON.xml"/>
  <play id="fre000043" file="ANSEAUME_CHINOIS.xml"/>
  <play id="fre000044" file="ANSEAUME_RESSOURCECOMIQUE.xml"/>
  <play id="fre000045" file="ARCHAMBAULT_CENESTPAS.xml"/>
  <play id="fre000046" file="ARCHAMBAULT_COMEDIEALIMPROMPTU.xml"/>
  <play id="fre000047" file="ARCHAMBAULT_ETRENNES.xml"/>
  <play id="fre000048" file="ARCHAMBAULT_HURLUBRELU.xml"/>
  <play id="fre000049" file="ARCHAMBAULT_JANOTBATTUS.xml"/>
  <play id="fre000050" file="ARCHAMBAULT_JANOTDEGRAISSEUR.xml"/>
  <play id="fre000051" file="ARCHAMBAULT_JOCRISSECHANGE.xml"/>
  <play id="fre000052" file="ARCHAMBAULT_ONFAITCEQUONPEUT.xml"/>
  <play id="fre000053" file="ARENE_NAZE.xml"/>
  <play id="fre000054" file="ARISTOPHANE_GUEPES.xml"/>
  <play id="fre000055" file="ARMAND_CRINATURE.xml"/>
  <play id="fre000056" file="ARNAULT_HORATIUSCOCLES.xml"/>
  <play id="fre000057" file="ARNOULD_HEROINEAMERICAINE.xml"/>
  <play id="fre000058" file="ARTAUD_CENTENAIREMOLIERE.xml"/>
  <play id="fre000059" file="AUBIGNAC_PUCELLE.xml"/>
  <play id="fre000060" file="AUBIGNAC_PUCELLE_PROSE.xml"/>
  <play id="fre000061" file="AUDE_ECOLETRAGIQUE.xml"/>
  <play id="fre000062" file="AUDIFFRET_ALBERTDURER.xml"/>
  <play id="fre000063" file="AUDIFFRET_COMEDIEAUCHATEAU.xml"/>
  <play id="fre000064" file="AUDIFFRET_EPREUVE.xml"/>
  <play id="fre000065" file="AUDINOT_DOROTHEE.xml"/>
  <play id="fre000066" file="AUDINOT_MUSICOMANIE.xml"/>
  <play id="fre000067" file="AURE_DIPNE.xml"/>
  <play id="fre000068" file="AURE_GENEVIEVE69.xml"/>
  <play id="fre000069" file="AURE_GENEVIEVE70.xml"/>
  <play id="fre000070" file="BACULARD_COLIGNI.xml"/>
  <play id="fre000071" file="BANVILLE_ANCIENPIERROT.xml"/>
  <play id="fre000072" file="BAPTISTEDUMOUTIER_MASCARADEFOIRESAINTGERMAIN.xml"/>
  <play id="fre000073" file="BARANTEDUFRESNY_FEES.xml"/>
  <play id="fre000074" file="BARANTEDUFRESNY_PASQUINMARFORIO.xml"/>
  <play id="fre000075" file="BARANTE_ARLEQUINMISANTHROPE.xml"/>
  <play id="fre000076" file="BARBIER_FAUCON.xml"/>
  <play id="fre000077" file="BARBIER_MORTDECESAR.xml"/>
  <play id="fre000078" file="BARBIER_OMBREDEMOLIERE.xml"/>
  <play id="fre000079" file="BARO_CELINDE.xml"/>
  <play id="fre000080" file="BARO_CLARIMONDE.xml"/>
  <play id="fre000081" file="BARO_CLORISE.xml"/>
  <play id="fre000082" file="BARO_PARTHENIE.xml"/>
  <play id="fre000083" file="BARO_PRINCEFUGITIF.xml"/>
  <play id="fre000084" file="BARO_SAINTEUSTACHE.xml"/>
  <play id="fre000085" file="BARQUEBOIS_RAPINIERE.xml"/>
  <play id="fre000086" file="BARRERADET_CANDIDE.xml"/>
  <play id="fre000087" file="BARREREDETDESFONTAINES_MARIGEDESCARRON.xml"/>
  <play id="fre000088" file="BAYART-ROMIEU_MOLIEREAUTHEATRE.xml"/>
  <play id="fre000089" file="BEAUMARCHAIS_AUTRETARTUFFE.xml"/>
  <play id="fre000090" file="BEAUMARCHAIS_BARBIERDESEVILLE.xml"/>
  <play id="fre000091" file="BEAUNOIR_AMOURQUETEUR.xml"/>
  <play id="fre000092" file="BEAUNOIR_CACOPHONIE.xml"/>
  <play id="fre000093" file="BEAUNOIR_LIBELLISTES.xml"/>
  <play id="fre000094" file="BEAUNOIR_PRINCERAMONEUR.xml"/>
  <play id="fre000095" file="BEAUNOIR_SCULPTEUR.xml"/>
  <play id="fre000096" file="BEAUNOIR_VENUS.xml"/>
  <play id="fre000097" file="BECQUE_DOMINOAQUATRE.xml"/>
  <play id="fre000098" file="BECQUE_EXECUTION.xml"/>
  <play id="fre000099" file="BECQUE_MERE.xml"/>
  <play id="fre000100" file="BECQUE_VEUVE.xml"/>
  <play id="fre000101" file="BENSERADE_CLEOPATRE.xml"/>
  <play id="fre000102" file="BENSERADE_MORTACHILLE.xml"/>
  <play id="fre000103" file="BERGASSE_JOURNEEDESDUPES.xml"/>
  <play id="fre000104" file="BERNARDC_MADAMEDEVAULDENAIE.xml"/>
  <play id="fre000105" file="BERNARDT_DRAMATURGEENPLEINLABEUR.xml"/>
  <play id="fre000106" file="BERNARDT_ECOLEDUPISTON.xml"/>
  <play id="fre000107" file="BERNARDT_ETRANGLEUSE.xml"/>
  <play id="fre000108" file="BERNARDT_MYSTERE.xml"/>
  <play id="fre000109" file="BERNARDT_NARCOTIQUE.xml"/>
  <play id="fre000110" file="BERNARDT_PARTIEDEBRIDGE.xml"/>
  <play id="fre000111" file="BERNARDT_PIEDSNICKELES.xml"/>
  <play id="fre000112" file="BERNARDT_PLAISIRSDUDIMANCHE.xml"/>
  <play id="fre000113" file="BERNARDT_PRETENDANT.xml"/>
  <play id="fre000114" file="BERNARDT_SACOCHE.xml"/>
  <play id="fre000115" file="BERNARD_BRUTUS.xml"/>
  <play id="fre000116" file="BERNARD_LAODAMIE.xml"/>
  <play id="fre000117" file="BERTOL-GRAIVIL_ALAMER.xml"/>
  <play id="fre000118" file="BERTON_HOMMEQUIATUELAMORT.xml"/>
  <play id="fre000119" file="BEYS_CELINE.xml"/>
  <play id="fre000120" file="BEZE_ABRAHAM.xml"/>
  <play id="fre000121" file="BIANCOLELLI-RICCOBONI-ROMAGNESI_COMEDIENSESCLAVES.xml"/>
  <play id="fre000122" file="BIANCOLELLI_ECOLEGALANTE.xml"/>
  <play id="fre000123" file="BIANCOLLELI_ENFANTSTROUVES.xml"/>
  <play id="fre000124" file="BIANCOLLELLIROMAGNESI_ARCAGAMBIS.xml"/>
  <play id="fre000125" file="BIANCOLLELLIROMAGNESI_BONNEFEMME.xml"/>
  <play id="fre000126" file="BIANCOLLELLI_AGNESDECHAILLOT.xml"/>
  <play id="fre000127" file="BIANCOLLELLI_ARLEQUINGENTILHOMME.xml"/>
  <play id="fre000128" file="BIANCOLLELLI_FOIREGALANTE.xml"/>
  <play id="fre000129" file="BIANCOLLELLI_OEDIPETRAVESTI.xml"/>
  <play id="fre000130" file="BIDEAUDEMONTIGNY_SEMIRAMIS.xml"/>
  <play id="fre000131" file="BIEVRE_SEDUCTEUR.xml"/>
  <play id="fre000132" file="BIEVRE_VERCINGENTORIXE.xml"/>
  <play id="fre000133" file="BILHAUD_PREMIERAMOUR.xml"/>
  <play id="fre000134" file="BILLARDONDESAUVIGNY_HIRZA.xml"/>
  <play id="fre000135" file="BILLARDONDESAUVIGNY_VASHINGTON.xml"/>
  <play id="fre000136" file="BILLARD_PLEUREURMALGRELUI.xml"/>
  <play id="fre000137" file="BIZET-SIMONOT_GILLESTOUTSEUL.xml"/>
  <play id="fre000138" file="BIZET_BOITES.xml"/>
  <play id="fre000139" file="BLANC_DRUIDES.xml"/>
  <play id="fre000140" file="BLANC_SUPPLICEDUNPAYSAN.xml"/>
  <play id="fre000141" file="BLEMONT-VALADE_BARBIERDEMOLIERE.xml"/>
  <play id="fre000142" file="BLEMONT_MOLIEREENBONNEFORTUNE.xml"/>
  <play id="fre000143" file="BLEMONT_PETITEROSANGE.xml"/>
  <play id="fre000144" file="BLEMONT_VISITEACORNEILLE.xml"/>
  <play id="fre000145" file="BOHAIRE_JESUSCHRIST.xml"/>
  <play id="fre000146" file="BOHAIRE_SIEGEDEPARIS.xml"/>
  <play id="fre000147" file="BOILEAU_HEROSDEROMAN.xml"/>
  <play id="fre000148" file="BOISROBERT_AMANTRIDICULE.xml"/>
  <play id="fre000149" file="BOISROBERT_BELLEINVISIBLE.xml"/>
  <play id="fre000150" file="BOISROBERT_CASSANDRE.xml"/>
  <play id="fre000151" file="BOISROBERT_RIVAUXAMIS.xml"/>
  <play id="fre000152" file="BOISSY_APOLOGIEDUSIECLE.xml"/>
  <play id="fre000153" file="BOISSY_AUTEURSUPERSTICIEUX.xml"/>
  <play id="fre000154" file="BOISSY_BABILLARD.xml"/>
  <play id="fre000155" file="BOISSY_COMTEDENEUILLY.xml"/>
  <play id="fre000156" file="BOISSY_CRITIQUEAUTEURSUPERSTICIEUX.xml"/>
  <play id="fre000157" file="BOISSY_DEHORSTROMPEURS.xml"/>
  <play id="fre000158" file="BOISSY_FRANCAISALONDRES.xml"/>
  <play id="fre000159" file="BOISSY_FRIVOLITE.xml"/>
  <play id="fre000160" file="BOISSY_HOMMEDUJOUR.xml"/>
  <play id="fre000161" file="BOISSY_JENESAISQUOI.xml"/>
  <play id="fre000162" file="BOISSY_MEDECINPAROCCASION.xml"/>
  <play id="fre000163" file="BOISSY_PLAGIAIRE.xml"/>
  <play id="fre000164" file="BOISSY_RIVALFAVORABLE.xml"/>
  <play id="fre000165" file="BOISSY_VIEESTUNSONGE.xml"/>
  <play id="fre000166" file="BONIFACE_OBELIXE.xml"/>
  <play id="fre000167" file="BONNETAIN_APRESLEDIVORCE.xml"/>
  <play id="fre000168" file="BONNETAIN_MAPOUPEE.xml"/>
  <play id="fre000169" file="BORNIER_QUINZEJANVIER.xml"/>
  <play id="fre000170" file="BORNIER_RACINE.xml"/>
  <play id="fre000171" file="BOUCHER_CHAMPAGNELECOIFFEUR.xml"/>
  <play id="fre000172" file="BOUILLY_DESCARTES.xml"/>
  <play id="fre000173" file="BOURSAULT_COMEDIESANSTITRE.xml"/>
  <play id="fre000174" file="BOURSAULT_DEUXFRERESGEMEAUX.xml"/>
  <play id="fre000175" file="BOURSAULT_ESOPE.xml"/>
  <play id="fre000176" file="BOURSAULT_FETEDELASEINE.xml"/>
  <play id="fre000177" file="BOURSAULT_GERMANICUS.xml"/>
  <play id="fre000178" file="BOURSAULT_JALOUXENDORMI.xml"/>
  <play id="fre000179" file="BOURSAULT_MARIESTUARD.xml"/>
  <play id="fre000180" file="BOURSAULT_MEDECINVOLANT.xml"/>
  <play id="fre000181" file="BOURSAULT_MORTVIVANT.xml"/>
  <play id="fre000182" file="BOURSAULT_MOTSALAMODE.xml"/>
  <play id="fre000183" file="BOURSAULT_PORTRAITDUPEINTRE.xml"/>
  <play id="fre000184" file="BOURSAULT_SATIREDESSATIRES.xml"/>
  <play id="fre000185" file="BOYERA_CATON.xml"/>
  <play id="fre000186" file="BOYER_AGAMEMNON.xml"/>
  <play id="fre000187" file="BOYER_AMOURSJUPITERSEMELE.xml"/>
  <play id="fre000188" file="BOYER_ARISTODEME.xml"/>
  <play id="fre000189" file="BOYER_ARTAXERCE.xml"/>
  <play id="fre000190" file="BOYER_CLOTILDE.xml"/>
  <play id="fre000191" file="BOYER_FEDERIC.xml"/>
  <play id="fre000192" file="BOYER_JEUNEMARIUS.xml"/>
  <play id="fre000193" file="BOYER_JUDITH.xml"/>
  <play id="fre000194" file="BOYER_LISIMENE.xml"/>
  <play id="fre000195" file="BOYER_MORTENFANTSBRUTE.xml"/>
  <play id="fre000196" file="BOYER_OROPASTE.xml"/>
  <play id="fre000197" file="BOYER_PORCIEROMAINE.xml"/>
  <play id="fre000198" file="BOYER_PORUS.xml"/>
  <play id="fre000199" file="BOYER_TIRIDATE.xml"/>
  <play id="fre000200" file="BRECOURT_OMBREDEMOLIERE.xml"/>
  <play id="fre000201" file="BROHAN_COMPTERSANSSONHOTE.xml"/>
  <play id="fre000202" file="BROHAN_QUIFEMMEAGUERREA.xml"/>
  <play id="fre000203" file="BROSSE_AVEUGLECLAIRVOYANT.xml"/>
  <play id="fre000204" file="BROSSE_TURNE.xml"/>
  <play id="fre000205" file="BRUEYSPALAPRAT_AVOCATPATELIN.xml"/>
  <play id="fre000206" file="BRULEBOEUF_RACINECHEZCORNEILLE.xml"/>
  <play id="fre000207" file="CADET-GASSICOURT_SOUPERDEMOLIERE.xml"/>
  <play id="fre000208" file="CAHUSAC_ZOROASTRE.xml"/>
  <play id="fre000209" file="CAILHAVA_EGOISME.xml"/>
  <play id="fre000210" file="CAILLEAU_TRAGEDIESVOLTAIRE.xml"/>
  <play id="fre000211" file="CAMPAN_DEUXEDUCATIONS.xml"/>
  <play id="fre000212" file="CAMPAN_FERMEPARTAGEE.xml"/>
  <play id="fre000213" file="CAMPISTRON_ACHILLE.xml"/>
  <play id="fre000214" file="CAMPISTRON_ACISGALATHEE.xml"/>
  <play id="fre000215" file="CAMPISTRON_ADRIEN.xml"/>
  <play id="fre000216" file="CAMPISTRON_AETIUS.xml"/>
  <play id="fre000217" file="CAMPISTRON_ALCIBIADE.xml"/>
  <play id="fre000218" file="CAMPISTRON_ANDRONIC.xml"/>
  <play id="fre000219" file="CAMPISTRON_ARMINIUSC.xml"/>
  <play id="fre000220" file="CAMPISTRON_JUBA.xml"/>
  <play id="fre000221" file="CAMPISTRON_PHOCION.xml"/>
  <play id="fre000222" file="CAMPISTRON_POMPEIA.xml"/>
  <play id="fre000223" file="CAMPISTRON_TACHMAS.xml"/>
  <play id="fre000224" file="CAMPISTRON_VIRGINIE.xml"/>
  <play id="fre000225" file="CARBONDEFLINS_MARIDIRECTEUR.xml"/>
  <play id="fre000226" file="CARBONDEFLINS_REVEILEPIMENIDE.xml"/>
  <play id="fre000227" file="CARMONTELLE_ABBEDECOUREDINER.xml"/>
  <play id="fre000228" file="CARMONTELLE_ABBEDEPLATRE.xml" wikidata="Q63368691"/>
  <play id="fre000229" file="CARMONTELLE_ABONCHATBONRAT.xml"/>
  <play id="fre000230" file="CARMONTELLE_ALMENORADE.xml"/>
  <play id="fre000231" file="CARMONTELLE_APRESDINEE.xml"/>
  <play id="fre000232" file="CARMONTELLE_ATROMPEURTROMPEURETDEMI.xml"/>
  <play id="fre000233" file="CARMONTELLE_AUTEURAVANTAGEUX.xml"/>
  <play id="fre000234" file="CARMONTELLE_AVOCATCHANSONNIER.xml"/>
  <play id="fre000235" file="CARMONTELLE_AVOCATCONSULTANT.xml"/>
  <play id="fre000236" file="CARMONTELLE_BAL.xml"/>
  <play id="fre000237" file="CARMONTELLE_BONS.xml"/>
  <play id="fre000238" file="CARMONTELLE_BOUDOIR.xml"/>
  <play id="fre000239" file="CARMONTELLE_CAFEBORGNE.xml"/>
  <play id="fre000240" file="CARMONTELLE_CHANTEURITALIEN.xml"/>
  <play id="fre000241" file="CARMONTELLE_CHAPONAUGROSEL.xml"/>
  <play id="fre000242" file="CARMONTELLE_CHASSEURJOUEURS.xml"/>
  <play id="fre000243" file="CARMONTELLE_CONDAMNEZSANSENTENDRE.xml"/>
  <play id="fre000244" file="CARMONTELLE_DESESPERESDELOPERA.xml"/>
  <play id="fre000245" file="CARMONTELLE_DEUXAMIS.xml"/>
  <play id="fre000246" file="CARMONTELLE_DEUXANGLAIS.xml"/>
  <play id="fre000247" file="CARMONTELLE_DEUXAUTEURS.xml"/>
  <play id="fre000248" file="CARMONTELLE_DEUXCHAPEAUX.xml"/>
  <play id="fre000249" file="CARMONTELLE_DIAMANT.xml"/>
  <play id="fre000250" file="CARMONTELLE_ECRIVAIN.xml"/>
  <play id="fre000251" file="CARMONTELLE_ENRAGE.xml"/>
  <play id="fre000252" file="CARMONTELLE_ETRANGER.xml"/>
  <play id="fre000253" file="CARMONTELLE_FAUXEMPOISONNEMENT.xml"/>
  <play id="fre000254" file="CARMONTELLE_FAUXINDIFFERENTS.xml"/>
  <play id="fre000255" file="CARMONTELLE_FOUS.xml"/>
  <play id="fre000256" file="CARMONTELLE_HISTOIRE.xml"/>
  <play id="fre000257" file="CARMONTELLE_IMPORTANT.xml"/>
  <play id="fre000258" file="CARMONTELLE_LIEVRE.xml"/>
  <play id="fre000259" file="CARMONTELLE_MAITREDEBALLETS.xml"/>
  <play id="fre000260" file="CARMONTELLE_MARIABSENT.xml"/>
  <play id="fre000261" file="CARMONTELLE_OFFICIERDUGOBELET.xml"/>
  <play id="fre000262" file="CARMONTELLE_PARI.xml"/>
  <play id="fre000263" file="CARMONTELLE_PEINTREENCULDESAC.xml"/>
  <play id="fre000264" file="CARMONTELLE_PETITMAITREPARPHILOSOPHIE.xml"/>
  <play id="fre000265" file="CARMONTELLE_PETITPOUCET.xml"/>
  <play id="fre000266" file="CARMONTELLE_PLEUREURSDHOMERE.xml"/>
  <play id="fre000267" file="CARMONTELLE_PORTRAIT.xml"/>
  <play id="fre000268" file="CARMONTELLE_POULET.xml"/>
  <play id="fre000269" file="CARMONTELLE_RECOMMANDATION.xml"/>
  <play id="fre000270" file="CARMONTELLE_SECONDESLOGES.xml"/>
  <play id="fre000271" file="CARMONTELLE_SEIGNEURAUTEUR.xml"/>
  <play id="fre000272" file="CARMONTELLE_SORTIEDELACOMEDIE.xml"/>
  <play id="fre000273" file="CARMONTELLE_SOURD.xml"/>
  <play id="fre000274" file="CARMONTELLE_STATUE.xml"/>
  <play id="fre000275" file="CARMONTELLE_SUISSEDEPORTE.xml"/>
  <play id="fre000276" file="CARMONTELLE_SUISSEMALADE.xml"/>
  <play id="fre000277" file="CARMONTELLE_VEUVEAVARE.xml"/>
  <play id="fre000278" file="CARMONTELLE_VOYAGEURS.xml"/>
  <play id="fre000279" file="CARRIERE-DOISIN_CAFELITTERAIRE.xml"/>
  <play id="fre000280" file="CARRIERE-DOISIN_JOURNEEDETITUS.xml"/>
  <play id="fre000281" file="CAYLUS_APPAREILLEUSE.xml"/>
  <play id="fre000282" file="CAYLUS_BORDEL.xml"/>
  <play id="fre000283" file="CEILLIER_COUSINEDGAR.xml"/>
  <play id="fre000284" file="CEROU_AMANTAUTEUR.xml"/>
  <play id="fre000285" file="CHABANON_EUDOXIE.xml"/>
  <play id="fre000286" file="CHABANON_FAUXNOBLE.xml"/>
  <play id="fre000287" file="CHABANON_TOISONDOR.xml"/>
  <play id="fre000288" file="CHAMFORT_LAJEUNEINDIENNE.xml"/>
  <play id="fre000289" file="CHAMFORT_MUSTAPHAZEANGIR.xml"/>
  <play id="fre000290" file="CHAMPMESLE_COUPEENCHANTEE.xml"/>
  <play id="fre000291" file="CHAMPMESLE_FRAGMENTSDEMOLIERE.xml"/>
  <play id="fre000292" file="CHAMPREPUS_ULYSSE.xml"/>
  <play id="fre000293" file="CHAPPUZEAU_ARMETZAR.xml"/>
  <play id="fre000294" file="CHAUVIN_COMMENCEMENTDELAFIN.xml"/>
  <play id="fre000295" file="CHAUVIN_RUSESETTRUCS.xml"/>
  <play id="fre000296" file="CHAZETDUBOIS_MOLIERECHEZNINON.xml"/>
  <play id="fre000297" file="CHAZETDUPATY_ARLEQUINJOURNALISTE.xml"/>
  <play id="fre000298" file="CHAZETGASSICOURT_FINOT.xml"/>
  <play id="fre000299" file="CHENIER_CHARLESIX.xml"/>
  <play id="fre000300" file="CHERON_HOMMEABONNESFORTUNES.xml"/>
  <play id="fre000301" file="CHEVALIER_AMOURSDECALOTIN.xml"/>
  <play id="fre000302" file="CHEVALIER_BARBONSAMOUREUX.xml"/>
  <play id="fre000303" file="CHEVALIER_CARTELDEGUILLOT.xml"/>
  <play id="fre000304" file="CHEVALIER_DESOLATIONDESFILOUS.xml"/>
  <play id="fre000305" file="CHEVALIER_DISGRACEDESDOMESTIQUES.xml"/>
  <play id="fre000306" file="CHEVALIER_GALANTSRIDICULES.xml"/>
  <play id="fre000307" file="CHEVALIER_INTRIGUEDESCARROSSES.xml"/>
  <play id="fre000308" file="CHEVALIER_PEDAGOGUEAMOUREUX.xml"/>
  <play id="fre000309" file="CHEVREAU_AVOCATDUPE.xml"/>
  <play id="fre000310" file="CINQAUTEURS_AVEUGLEDESMYRNE.xml"/>
  <play id="fre000311" file="CINQAUTEURS_COMEDIEDESTUILERIES.xml"/>
  <play id="fre000312" file="CLARETIE_VALENTIN.xml"/>
  <play id="fre000313" file="COLARDEAU_ASTARBE.xml"/>
  <play id="fre000314" file="COLLEVILLE_SOPHIEDERVILLE.xml"/>
  <play id="fre000315" file="COLLE_ACCIDENTS.xml"/>
  <play id="fre000316" file="COLLE_ALFONSE.xml"/>
  <play id="fre000317" file="COLLE_COCATRIX.xml"/>
  <play id="fre000318" file="COLLE_ESPERANCE.xml"/>
  <play id="fre000319" file="COLLE_ILESONNANTE.xml"/>
  <play id="fre000320" file="CONSTANT_WALLSTEIN.xml"/>
  <play id="fre000321" file="CORNEILLEP_AGESILAS.xml" slug="corneillep-agesilas" wikidata="Q2827379"/>
  <play id="fre000322" file="CORNEILLEP_ANDROMEDE.xml" slug="corneillep-andromede" wikidata="Q2846944"/>
  <play id="fre000323" file="CORNEILLEP_ATTILA.xml" wikidata="Q2870103"/>
  <play id="fre000324" file="CORNEILLEP_CID.xml" wikidata="Q637787"/>
  <play id="fre000325" file="CORNEILLEP_CID37.xml" wikidata="Q637787"/>
  <play id="fre000326" file="CORNEILLEP_CINNA.xml" wikidata="Q2972822"/>
  <play id="fre000327" file="CORNEILLEP_CINNA43.xml" wikidata="Q2972822"/>
  <play id="fre000328" file="CORNEILLEP_CLITANDRE.xml" wikidata="Q2979399"/>
  <play id="fre000329" file="CORNEILLEP_DONSANCHE.xml" slug="corneillep-don-sanche-d-aragon" wikidata="Q15936594"/>
  <play id="fre000330" file="CORNEILLEP_GALERIEDUPALAIS.xml" slug="corneillep-la-galerie-du-palais" wikidata="Q15952083"/>
  <play id="fre000331" file="CORNEILLEP_HERACLIUS.xml" slug="corneillep-heraclius-empereur-d-orient" wikidata="Q3144997"/>
  <play id="fre000332" file="CORNEILLEP_HORACE.xml" wikidata="Q2574569"/>
  <play id="fre000333" file="CORNEILLEP_ILLUSIONCOMIQUE.xml" wikidata="Q2281691"/>
  <play id="fre000334" file="CORNEILLEP_MEDEE.xml" wikidata="Q3332723"/>
  <play id="fre000335" file="CORNEILLEP_MEDEE39.xml" wikidata="Q3332723"/>
  <play id="fre000336" file="CORNEILLEP_MELITE.xml" wikidata="Q16386962"/>
  <play id="fre000337" file="CORNEILLEP_MELITE33.xml" wikidata="Q16386962"/>
  <play id="fre000338" file="CORNEILLEP_MENTEUR.xml" wikidata="Q3224493"/>
  <play id="fre000339" file="CORNEILLEP_MORTPOMPEE.xml" wikidata="Q933030"/>
  <play id="fre000340" file="CORNEILLEP_NICOMEDE.xml" wikidata="Q3341201"/>
  <play id="fre000341" file="CORNEILLEP_OEDIPE.xml" wikidata="Q3594073"/>
  <play id="fre000342" file="CORNEILLEP_OTHON.xml" wikidata="Q3357625"/>
  <play id="fre000343" file="CORNEILLEP_PERTHARITE.xml" wikidata="Q3376170"/>
  <play id="fre000344" file="CORNEILLEP_PLACEROYALE.xml" wikidata="Q3211684"/>
  <play id="fre000345" file="CORNEILLEP_POLYEUCTE.xml" wikidata="Q546217"/>
  <play id="fre000346" file="CORNEILLEP_PULCHERIE.xml" wikidata="Q3410736"/>
  <play id="fre000347" file="CORNEILLEP_RODOGUNE.xml" wikidata="Q2161210"/>
  <play id="fre000348" file="CORNEILLEP_SERTORIUS.xml" wikidata="Q2365486"/>
  <play id="fre000349" file="CORNEILLEP_SOPHONISBE.xml" wikidata="Q3491092"/>
  <play id="fre000350" file="CORNEILLEP_SUITEMENTEUR.xml" wikidata="Q15986637"/>
  <play id="fre000351" file="CORNEILLEP_SUIVANTE.xml" wikidata="Q15986590"/>
  <play id="fre000352" file="CORNEILLEP_SURENA.xml" wikidata="Q3505546"/>
  <play id="fre000353" file="CORNEILLEP_THEODORE.xml" wikidata="Q3526380"/>
  <play id="fre000354" file="CORNEILLEP_TITE.xml" wikidata="Q3529531"/>
  <play id="fre000355" file="CORNEILLEP_TOISON.xml" wikidata="Q3213166"/>
  <play id="fre000356" file="CORNEILLEP_VEUVE.xml" wikidata="Q3213532"/>
  <play id="fre000357" file="CORNEILLEP_VEUVE34.xml" wikidata="Q3213532"/>
  <play id="fre000358" file="CORNEILLET_AMOURALAMODE.xml"/>
  <play id="fre000359" file="CORNEILLET_ANTIOCHUS.xml"/>
  <play id="fre000360" file="CORNEILLET_ARIANE.xml" wikidata="Q2861171"/>
  <play id="fre000361" file="CORNEILLET_BERENICE.xml"/>
  <play id="fre000362" file="CORNEILLET_BERGEREXTRAVAGANT.xml"/>
  <play id="fre000363" file="CORNEILLET_BRADAMANTE.xml"/>
  <play id="fre000364" file="CORNEILLET_CAMMA.xml"/>
  <play id="fre000365" file="CORNEILLET_CHARMEDELAVOIX.xml"/>
  <play id="fre000366" file="CORNEILLET_CIRCE.xml"/>
  <play id="fre000367" file="CORNEILLET_COMTEDESSEX.xml" wikidata="Q30742461"/>
  <play id="fre000368" file="CORNEILLET_COMTESSEORGUEIL.xml"/>
  <play id="fre000369" file="CORNEILLET_DARIUS.xml"/>
  <play id="fre000370" file="CORNEILLET_DOMBERTRANDECIGARRAL.xml"/>
  <play id="fre000371" file="CORNEILLET_DOMCESARDAVALOS.xml"/>
  <play id="fre000372" file="CORNEILLET_ENGAGEMENTSDUHASARD.xml"/>
  <play id="fre000373" file="CORNEILLET_FEINTASTROLOGUE.xml"/>
  <play id="fre000374" file="CORNEILLET_FESTINPIERRE.xml"/>
  <play id="fre000375" file="CORNEILLET_GALANTDOUBLE.xml"/>
  <play id="fre000376" file="CORNEILLET_GEOLIERDESOISMEME.xml"/>
  <play id="fre000377" file="CORNEILLET_ILLUSTRESENNEMIS.xml"/>
  <play id="fre000378" file="CORNEILLET_INCONNU.xml"/>
  <play id="fre000379" file="CORNEILLET_LAODICE.xml"/>
  <play id="fre000380" file="CORNEILLET_MAXIMIAN.xml"/>
  <play id="fre000381" file="CORNEILLET_MEDEE.xml" wikidata="Q1520514"/>
  <play id="fre000382" file="CORNEILLET_MORTANNIBAL.xml"/>
  <play id="fre000383" file="CORNEILLET_MORTDACHILLE.xml"/>
  <play id="fre000384" file="CORNEILLET_MORTEMPEREURCOMMODE.xml"/>
  <play id="fre000385" file="CORNEILLET_PERSEEDEMETRIUS.xml"/>
  <play id="fre000386" file="CORNEILLET_PYRRHUS.xml"/>
  <play id="fre000387" file="CORNEILLET_STLICON.xml"/>
  <play id="fre000388" file="CORNEILLET_THEODAT.xml"/>
  <play id="fre000389" file="CORNEILLET_TIMOCRATE.xml" wikidata="Q48747142"/>
  <play id="fre000390" file="COUPIGNYBARREPIISDESFONTAINES_HOMMAGERACINE.xml" slug="coupigny-barre-piis-radet-desfontaines-hommage-du-petit-vaudeville-au-grand_racine"/>
  <play id="fre000391" file="COUPIGNY_ARLEQUINJALOUX.xml"/>
  <play id="fre000392" file="COURTELINE_CONVERSIONDALCESTE.xml"/>
  <play id="fre000393" file="COURTELINE_MONSIEURBADIN.xml"/>
  <play id="fre000394" file="COURTELINE_ROLAND.xml"/>
  <play id="fre000395" file="COURTELINE_THEODORECHERCHEDESALUMETTES.xml"/>
  <play id="fre000396" file="CREBILLONF_NUITETLEMOMENT.xml"/>
  <play id="fre000397" file="CREBILLON_ATREETHYESTE.xml" wikidata="Q2380886"/>
  <play id="fre000398" file="CREBILLON_CATILINA.xml" wikidata="Q19143603"/>
  <play id="fre000399" file="CREBILLON_ELECTRE.xml" wikidata="Q3587590"/>
  <play id="fre000400" file="CREBILLON_IDOMENEE.xml" wikidata="Q3147904"/>
  <play id="fre000401" file="CREBILLON_PYRRHUS.xml" wikidata=""/>
  <play id="fre000402" file="CREBILLON_RHADAMISTHE.xml" wikidata="Q3429083"/>
  <play id="fre000403" file="CREBILLON_SEMIRAMIS.XML" wikidata="Q19231742"/>
  <play id="fre000404" file="CREBILLON_TRIUMVIRAT.xml"/>
  <play id="fre000405" file="CREBILLON_XERXES.xml"/>
  <play id="fre000406" file="CRESSONNOIS_MONSIEURQUINEVEUTPASFUMER.xml"/>
  <play id="fre000407" file="CROS_AFFAIREDELARUEBEAUBOURG.xml"/>
  <play id="fre000408" file="CROS_AUTREFOIS.xml"/>
  <play id="fre000409" file="CROS_CAPITALISTE.xml"/>
  <play id="fre000410" file="CROS_HARENGSAUR.xml"/>
  <play id="fre000411" file="CROS_MAITREDARMES.xml"/>
  <play id="fre000412" file="CROS_OBSESSION.xml"/>
  <play id="fre000413" file="CROS_VOYAGEATROISETOILES.xml"/>
  <play id="fre000414" file="CUBIERES-PALMEZEAUX_BRACELETS.xml"/>
  <play id="fre000415" file="CUBIERES-PALMEZEAUX_DIALOGUE.xml"/>
  <play id="fre000416" file="CUBIERES-PALMEZEAUX_DILIGENCEDELYON.xml"/>
  <play id="fre000417" file="CUBIERES-PALMEZEAUX_FETESECULAIRECORNEILLE.xml"/>
  <play id="fre000418" file="CUBIERES-PALMEZEAUX_GALATHEE.xml"/>
  <play id="fre000419" file="CUBIERES-PALMEZEAUX_LACRYMANIE.xml"/>
  <play id="fre000420" file="CUBIERES-PALMEZEAUX_MORTDEMOLIERE3A.xml"/>
  <play id="fre000421" file="CUBIERES-PALMEZEAUX_MORTDEMOLIERE4A.xml"/>
  <play id="fre000422" file="CUBIERES-PALMEZEAUX_ORESTE.xml"/>
  <play id="fre000423" file="CYRANO_LAMORTDAGRIPPINE.xml"/>
  <play id="fre000424" file="CYRANO_PEDANTJOUE.xml"/>
  <play id="fre000425" file="DALIBRAY_SOLIMAN.xml"/>
  <play id="fre000426" file="DANCOURT_AGIOTEURS.xml"/>
  <play id="fre000427" file="DANCOURT_AMANTS.xml"/>
  <play id="fre000428" file="DANCOURT_BONSOLDAT.xml"/>
  <play id="fre000429" file="DANCOURT_BOURGEOISESALAMODE.xml"/>
  <play id="fre000430" file="DANCOURT_CEPHALEPROCRIS.xml"/>
  <play id="fre000431" file="DANCOURT_CHARIVARI.xml"/>
  <play id="fre000432" file="DANCOURT_CHEVALIERALAMODE.xml"/>
  <play id="fre000433" file="DANCOURT_COLIN-MAILLARD.xml"/>
  <play id="fre000434" file="DANCOURT_COMEDIECOMEDIENS.xml"/>
  <play id="fre000435" file="DANCOURT_CURIEUX.xml"/>
  <play id="fre000436" file="DANCOURT_DEROUTEPHARAON.xml"/>
  <play id="fre000437" file="DANCOURT_DESOLATIONDESJOUEUSES.xml"/>
  <play id="fre000438" file="DANCOURT_DIABLEBOITEUX.xml"/>
  <play id="fre000439" file="DANCOURT_DIABLEBOITEUXSUITE.xml"/>
  <play id="fre000440" file="DANCOURT_DIVERTISSEMENTDESCEAUX.xml"/>
  <play id="fre000441" file="DANCOURT_EAUXDEBOURBON.xml"/>
  <play id="fre000442" file="DANCOURT_ENFANTSDEPARIS.xml"/>
  <play id="fre000443" file="DANCOURT_ETEDESCOQUETTES.xml"/>
  <play id="fre000444" file="DANCOURT_FEES.xml"/>
  <play id="fre000445" file="DANCOURT_FEMMEDINTRIGUES.xml"/>
  <play id="fre000446" file="DANCOURT_FETEDEVILLAGE.xml"/>
  <play id="fre000447" file="DANCOURT_FETESNOCTURNES.xml"/>
  <play id="fre000448" file="DANCOURT_FOIREDEBESONS.xml"/>
  <play id="fre000449" file="DANCOURT_FOIRESAINTGERMAIN.xml"/>
  <play id="fre000450" file="DANCOURT_FOLLEENCHERE.xml"/>
  <play id="fre000451" file="DANCOURT_FONDSPERDUS.xml"/>
  <play id="fre000452" file="DANCOURT_GALANTJARDINIER.xml"/>
  <play id="fre000453" file="DANCOURT_GAZETTE.xml"/>
  <play id="fre000454" file="DANCOURT_IMPROMPTUDEGARNISON.xml"/>
  <play id="fre000455" file="DANCOURT_IMPROMPTUDELIVRY.xml"/>
  <play id="fre000456" file="DANCOURT_IMPROMPTUSURESNES.xml"/>
  <play id="fre000457" file="DANCOURT_INCONNU.xml"/>
  <play id="fre000458" file="DANCOURT_LOTERIE.xml"/>
  <play id="fre000459" file="DANCOURT_MADAMEARTUS.xml"/>
  <play id="fre000460" file="DANCOURT_MAISONDECAMPAGNE.xml"/>
  <play id="fre000461" file="DANCOURT_MARIRETROUVE.xml"/>
  <play id="fre000462" file="DANCOURT_METEMPSYCHOSE.xml"/>
  <play id="fre000463" file="DANCOURT_MOULINDEJAVELLE.xml"/>
  <play id="fre000464" file="DANCOURT_OPERADEVILLAGE.xml"/>
  <play id="fre000465" file="DANCOURT_OPERATEURBARRY.xml"/>
  <play id="fre000466" file="DANCOURT_PARISIENNE.xml"/>
  <play id="fre000467" file="DANCOURT_PRIXARQUEBUSE.xml"/>
  <play id="fre000468" file="DANCOURT_RENAUDARMIDE.xml"/>
  <play id="fre000469" file="DANCOURT_RETOURDESOFFICIERS.xml"/>
  <play id="fre000470" file="DANCOURT_SANCHO.xml"/>
  <play id="fre000471" file="DANCOURT_TRAHISONPUNIE.xml"/>
  <play id="fre000472" file="DANCOURT_TUTEUR.xml"/>
  <play id="fre000473" file="DANCOURT_VACANCES.xml"/>
  <play id="fre000474" file="DANCOURT_VENDANGES.xml"/>
  <play id="fre000475" file="DANCOURT_VENDANGESDESURESNES.xml"/>
  <play id="fre000476" file="DANCOURT_VERTGALANT.xml"/>
  <play id="fre000477" file="DECAUX_MARIUS.xml"/>
  <play id="fre000478" file="DELAVIGNE_COMEDIENS.xml"/>
  <play id="fre000479" file="DELAVIGNE_FAMILLETEMPSLUTHER.xml"/>
  <play id="fre000480" file="DELAVIGNE_VEPRESSICILIENNES.xml"/>
  <play id="fre000481" file="DESESSARTS_ILLUSTRETHEATRE.xml"/>
  <play id="fre000482" file="DESFONTAINES-DUPIN_VOYAGEDECHAMBORD.xml"/>
  <play id="fre000483" file="DESFONTAINES_EURIMEDON.xml"/>
  <play id="fre000484" file="DESFONTAINES_PERSIDE.xml"/>
  <play id="fre000485" file="DESFONTAINES_SAINTGENEST.xml"/>
  <play id="fre000486" file="DESFONTAINES_VERITABLESEMIRAMIS.xml"/>
  <play id="fre000487" file="DESHOULIERES_GENSERIC.xml"/>
  <play id="fre000488" file="DESHOULIERES_MORTDECOCHON.xml"/>
  <play id="fre000489" file="DESJARDINS_FAVORI.xml"/>
  <play id="fre000490" file="DESJARDINS_MANLIUS.xml"/>
  <play id="fre000491" file="DESLISLE_ARLEQUINSAUVAGE.xml"/>
  <play id="fre000492" file="DESMAREST_MIRAME.xml"/>
  <play id="fre000493" file="DESMARES_MERLINDRAGON.xml"/>
  <play id="fre000494" file="DESMARES_ROXELANE.xml"/>
  <play id="fre000495" file="DESMARETS_VISIONNAIRES.xml"/>
  <play id="fre000496" file="DESPORTES_VEUVECOQUETTE.xml"/>
  <play id="fre000497" file="DIDEROT_ESTILBONESTILMECHANT.xml" wikidata="Q3058772"/>
  <play id="fre000498" file="DIDEROT_FILSNATUREL.xml" wikidata="Q3222842"/>
  <play id="fre000499" file="DIDEROT_PARADOXECOMEDIEN.xml" wikidata="Q3363343"/>
  <play id="fre000500" file="DIDEROT_PEREDEFAMILLE.xml" wikidata="Q3226137"/>
  <play id="fre000501" file="DIDEROT_PIECEPROLOGUE.xml"/>
  <play id="fre000502" file="DISCRET_NOCESDEVAUGIRARD.xml"/>
  <play id="fre000503" file="DONNEAUDEVISE-CORNEILLE_DEVINERESSE.xml"/>
  <play id="fre000504" file="DONNEAUDEVISE_AMOURSDUSOLEIL.xml"/>
  <play id="fre000505" file="DONNEAUDEVISE_COCUEIMAGINAIRE.xml"/>
  <play id="fre000506" file="DONNEAUDEVISE_DAMESVENGEES.xml"/>
  <play id="fre000507" file="DONNEAUDEVISE_DELIE.xml"/>
  <play id="fre000508" file="DONNEAUDEVISE_EMBARRASDEGODARD.xml"/>
  <play id="fre000509" file="DONNEAUDEVISE_GENTILHOMMEGUEPIN.xml"/>
  <play id="fre000510" file="DONNEAUDEVISE_INTRIGUESDELALOTERIE.xml"/>
  <play id="fre000511" file="DONNEAUDEVISE_MERECOQUETTE.xml"/>
  <play id="fre000512" file="DONNEAUDEVISE_VENGEANCEDESMARQUIS.xml"/>
  <play id="fre000513" file="DONNEAUDEVISE_VEUVEALAMODE.xml"/>
  <play id="fre000514" file="DONNEAUDEVISE_ZELINDE.xml"/>
  <play id="fre000515" file="DORAT_CELIBATAIRE.xml"/>
  <play id="fre000516" file="DORAT_REGULUS.xml"/>
  <play id="fre000517" file="DORIMOND_AMOURSDETRAPOLIN.xml"/>
  <play id="fre000518" file="DORIMOND_COMEDIEDELACOMEDIE.xml"/>
  <play id="fre000519" file="DORIMOND_ECOLEDESCOCUS.xml"/>
  <play id="fre000520" file="DORIMOND_FEMMEINDUSTRIEUSE.xml"/>
  <play id="fre000521" file="DORNEVALFUZELIERLESAGE_ARLEQUINROIDESOGRES.xml"/>
  <play id="fre000522" file="DORNEVALLESAGE_AMOURSDENANTERRE.xml"/>
  <play id="fre000523" file="DORNEVALLESAGE_COUPLETSENPROCES.xml"/>
  <play id="fre000524" file="DORNEVALLESAGE_OPERACOMIQUE.xml"/>
  <play id="fre000525" file="DORNEVALLESAGE_REINEDEBAROSTAN.xml"/>
  <play id="fre000526" file="DORNEVAL_JUGEMENTDEPARIS.xml"/>
  <play id="fre000527" file="DORUXIGNE_ALZATE.xml"/>
  <play id="fre000528" file="DORVO_LAMENTIN.xml"/>
  <play id="fre000529" file="DUBOSC_BALANCEDETAT.xml"/>
  <play id="fre000530" file="DUCHE_ABSALON.xml"/>
  <play id="fre000531" file="DUFRESNYREGNARD_AUGMENTATIONBAGUETTE.xml"/>
  <play id="fre000532" file="DUFRESNYREGNARD_BAGUETTEVULCAIN.xml"/>
  <play id="fre000533" file="DUFRESNYREGNARD_CHINOIS.xml"/>
  <play id="fre000534" file="DUFRESNYREGNARD_NAISSANCEDAMADIS.xml"/>
  <play id="fre000535" file="DUFRESNYREGNARD_SUITEFOIRESAINTGERMAIN.xml"/>
  <play id="fre000536" file="DUFRESNY_ADIEUXDESOFFICIERS.xml"/>
  <play id="fre000537" file="DUFRESNY_CHEVALIERJOUEUR.xml"/>
  <play id="fre000538" file="DUFRESNY_COQUETTEDUVILLAGE.xml"/>
  <play id="fre000539" file="DUFRESNY_DEDIT.xml"/>
  <play id="fre000540" file="DUFRESNY_DEPARTDESCOMEDIENS.xml"/>
  <play id="fre000541" file="DUFRESNY_DOUBLEVEUVAGE.xml"/>
  <play id="fre000542" file="DUFRESNY_ESPRITDECONTRADICTION.xml"/>
  <play id="fre000543" file="DUFRESNY_FAUXHONNETEHOMME.xml"/>
  <play id="fre000544" file="DUFRESNY_FAUXINSTINCT.xml"/>
  <play id="fre000545" file="DUFRESNY_FAUXSINCERE.xml"/>
  <play id="fre000546" file="DUFRESNY_JALOUXHONTEUX.xml"/>
  <play id="fre000547" file="DUFRESNY_JOUEUSE.xml"/>
  <play id="fre000548" file="DUFRESNY_MALADESANSMALADIE.xml"/>
  <play id="fre000549" file="DUFRESNY_MALASSORTIS.xml"/>
  <play id="fre000550" file="DUFRESNY_MARIAGEFAITETROMPU.xml"/>
  <play id="fre000551" file="DUFRESNY_NEGLIGENT.xml"/>
  <play id="fre000552" file="DUFRESNY_NOCEINTERROMPUE.xml"/>
  <play id="fre000553" file="DUFRESNY_RECONCILIATIONNORMANDE.xml"/>
  <play id="fre000554" file="DUGAZON_MODERE.xml"/>
  <play id="fre000555" file="DUHOMME_CHAPELLEBOILEAU.xml"/>
  <play id="fre000556" file="DUMANIANT_BELLEESCLAVE.xml"/>
  <play id="fre000557" file="DUMANIANT_DRAGONDETHIONVILLE.xml"/>
  <play id="fre000558" file="DUMANIANT_FRANCAISENHURONIE.xml"/>
  <play id="fre000559" file="DUMANIANT_FRANCAISENHURONIE_1787.xml"/>
  <play id="fre000560" file="DUMANIANT_HENRIETPERRINE.xml"/>
  <play id="fre000561" file="DUMANIANT_JODELET.xml"/>
  <play id="fre000562" file="DUMAS_DONJUAN.xml"/>
  <play id="fre000563" file="DUPATY-LUCE-SALVERTE_BIEVRE.xml"/>
  <play id="fre000564" file="DUPATY_ARLEQUINTOUTSEUL.xml"/>
  <play id="fre000565" file="DUPONTDEVEYLE_SOMNANBULE.xml"/>
  <play id="fre000566" file="DURANT_ABONCHATBONRAT.xml"/>
  <play id="fre000567" file="DURANT_ALAVERLATETE.xml"/>
  <play id="fre000568" file="DURANT_BONNERENOMMEE.xml"/>
  <play id="fre000569" file="DURANT_JOURSSESUIVENT.xml"/>
  <play id="fre000570" file="DURANT_OISIVETE.xml"/>
  <play id="fre000571" file="DURANT_ONNECONNAITPASLEVIN.xml"/>
  <play id="fre000572" file="DURANT_POURUNPLAISIRMILLEDOULEURS.xml"/>
  <play id="fre000573" file="DURANT_QUICOURTDEUXLIEVRES.xml"/>
  <play id="fre000574" file="DURANT_TELMAITRETELVALET.xml"/>
  <play id="fre000575" file="DURANT_VOYAGEDECAMPAGNE.xml"/>
  <play id="fre000576" file="DURYER_ALCIMEDON.xml"/>
  <play id="fre000577" file="DURYER_ALCIONEE.xml"/>
  <play id="fre000578" file="DURYER_ANAXANDRE.xml"/>
  <play id="fre000579" file="DURYER_ARGENISPOLIARQUE.xml"/>
  <play id="fre000580" file="DURYER_BERENICE.xml"/>
  <play id="fre000581" file="DURYER_CLARIGENE.xml"/>
  <play id="fre000582" file="DURYER_CLEOMEDON.xml"/>
  <play id="fre000583" file="DURYER_CLITOPHON.xml"/>
  <play id="fre000584" file="DURYER_DYNAMIS.xml"/>
  <play id="fre000585" file="DURYER_ESTHER.xml"/>
  <play id="fre000586" file="DURYER_LISANDRECALISTE.xml"/>
  <play id="fre000587" file="DURYER_LUCRECE.xml"/>
  <play id="fre000588" file="DURYER_NITOCRIS.xml"/>
  <play id="fre000589" file="DURYER_SAUL.xml"/>
  <play id="fre000590" file="DURYER_SCEVOLE.xml"/>
  <play id="fre000591" file="DURYER_THEMISTOCLE.xml"/>
  <play id="fre000592" file="DURYER_VENDANGESDESURESNES.xml"/>
  <play id="fre000593" file="DUVAUCHEL_SAMEDISOIR.xml"/>
  <play id="fre000594" file="DUVAUCUEL_CHAPEAUBLEU.xml"/>
  <play id="fre000595" file="DUVERT-XAVIER_ODEINA.xml"/>
  <play id="fre000596" file="DUVERT_HURON.xml"/>
  <play id="fre000597" file="ECKER_FRANCMACONPRISONNIER.xml"/>
  <play id="fre000598" file="ESCHYLE_AGAMEMNON.xml"/>
  <play id="fre000599" file="ESCHYLE_EUMENIDES.xml"/>
  <play id="fre000600" file="ESCHYLE_KHOEPHORES.xml"/>
  <play id="fre000601" file="ESCHYLE_SEPTCONTRETHEBES.xml"/>
  <play id="fre000602" file="EURIPIDE_ANDROMAQUE.xml"/>
  <play id="fre000603" file="EURIPIDE_CYCLOPE.xml"/>
  <play id="fre000604" file="EURIPIDE_ELECTRE.xml"/>
  <play id="fre000605" file="EURIPIDE_HELENE.xml"/>
  <play id="fre000606" file="EURIPIDE_HERACLIDES.xml"/>
  <play id="fre000607" file="EURIPIDE_HERCULEFURIEUX.xml"/>
  <play id="fre000608" file="EURIPIDE_HIPPOLYTE.xml"/>
  <play id="fre000609" file="FABIE_MOLIEREMONTESPAN.xml"/>
  <play id="fre000610" file="FABREDEGLANTINE_PHILINTEDEMOLIERE.xml"/>
  <play id="fre000611" file="FAGAN_ISABELLEARLEQUIN.xml"/>
  <play id="fre000612" file="FAGAN_MOMUSAPARIS.xml"/>
  <play id="fre000613" file="FAGAN_PUPILLE.xml"/>
  <play id="fre000614" file="FAGAN_SYLPHESUPPOSE.xml"/>
  <play id="fre000615" file="FAVARD_AMANTDEGUISE.xml"/>
  <play id="fre000616" file="FAVART-PARMENTIER_HIPOLYTEARICIE.xml"/>
  <play id="fre000617" file="FAVART_ACAJOU.xml"/>
  <play id="fre000618" file="FAVART_ANGLAISDEBORDEAUX.xml" wikidata="Q3202020"/>
  <play id="fre000619" file="FAVART_LAFILLEMALGARDEE.xml"/>
  <play id="fre000620" file="FENELON_ALEXANDRE.xml"/>
  <play id="fre000621" file="FERRIER_LARMEDAUVERGNAT.xml"/>
  <play id="fre000622" file="FEYDEAU_AMOURETPIANO.xml"/>
  <play id="fre000623" file="FEYDEAU_ANTIPODES.xml"/>
  <play id="fre000624" file="FEYDEAU_BILLETDEMILLE.xml"/>
  <play id="fre000625" file="FEYDEAU_CELEBRES.xml"/>
  <play id="fre000626" file="FEYDEAU_CESTUNEFEMMEDUMONDE.xml"/>
  <play id="fre000627" file="FEYDEAU_COLIS.xml"/>
  <play id="fre000628" file="FEYDEAU_COMPLAINTEDUPAUVPRORIETAIRE.xml"/>
  <play id="fre000629" file="FEYDEAU_ENFANTS.xml"/>
  <play id="fre000630" file="FEYDEAU_HOMMEQUINAIMAITPASLESMONOLOGUES.xml"/>
  <play id="fre000631" file="FEYDEAU_JAIMALAUXDENTS.xml"/>
  <play id="fre000632" file="FEYDEAU_JURE.xml"/>
  <play id="fre000633" file="FEYDEAU_MONSIEURQUIESTCONDAMNE.xml"/>
  <play id="fre000634" file="FEYDEAU_MOUCHOIR.xml"/>
  <play id="fre000635" file="FEYDEAU_NOTREFUTUR.xml"/>
  <play id="fre000636" file="FEYDEAU_PATTEENLAIR.xml"/>
  <play id="fre000637" file="FEYDEAU_PETITEREVOLTEE.xml"/>
  <play id="fre000638" file="FEYDEAU_PETITMENAGE.xml"/>
  <play id="fre000639" file="FEYDEAU_POTACHE.xml"/>
  <play id="fre000640" file="FEYDEAU_TOUTABROWNSEQUARD.xml"/>
  <play id="fre000641" file="FEYDEAU_TROPVIEUX.xml"/>
  <play id="fre000642" file="FEYDEAU_UNCOUPDETETE.xml"/>
  <play id="fre000643" file="FIEVRE_MOLIEREAQUEBEC.xml"/>
  <play id="fre000644" file="FIOT_AMOURFANTASQUE.xml"/>
  <play id="fre000645" file="FLORIAN_BONMENAGE.xml"/>
  <play id="fre000646" file="FLORIAN_BONPERE.xml"/>
  <play id="fre000647" file="FLORIAN_DEUXBILLETS.xml"/>
  <play id="fre000648" file="FLORIAN_HEROLEANDRE.xml"/>
  <play id="fre000649" file="FLORIAN_JUMEAUXDEBERGAME.xml"/>
  <play id="fre000650" file="FOLARD_THEMISTOCLE.xml"/>
  <play id="fre000651" file="FONTENELLE_ENDYMION.xml"/>
  <play id="fre000652" file="FOURNIER_FILLEDEMOLIERE.xml"/>
  <play id="fre000653" file="FOURNIER_RACINEAUZES.xml"/>
  <play id="fre000654" file="FUZELIERLEGRAND_ANIMAUXRAISONNABLES.xml"/>
  <play id="fre000655" file="FUZELIERLESAGE_TABLEAUDUMARIAGE.xml"/>
  <play id="fre000656" file="FUZELIER_ENFERGALANT.xml"/>
  <play id="fre000657" file="FUZELIER_ORPHEE.xml"/>
  <play id="fre000658" file="FUZELIER_SCARAMOUCHEPEDANT.xml"/>
  <play id="fre000659" file="GABRIEL-LABOULLAYE_JOSEPHINE.xml"/>
  <play id="fre000660" file="GALOPPE_AMOURPRISAUXCHEVEUX.xml"/>
  <play id="fre000661" file="GARNIERT_ADELAIDE.xml"/>
  <play id="fre000662" file="GARNIERT_BELLEMERE.xml"/>
  <play id="fre000663" file="GARNIERT_BIENFAITRECOMPENSE.xml"/>
  <play id="fre000664" file="GARNIERT_BONPAPA.xml"/>
  <play id="fre000665" file="GARNIERT_BONPERE.xml"/>
  <play id="fre000666" file="GARNIERT_BOURSE.xml"/>
  <play id="fre000667" file="GARNIERT_BRUNON.xml"/>
  <play id="fre000668" file="GARNIERT_DEDIT.xml"/>
  <play id="fre000669" file="GARNIERT_DEUXPATES.xml"/>
  <play id="fre000670" file="GARNIERT_DISSIPATRICE.xml"/>
  <play id="fre000671" file="GARNIERT_EPREUVE.xml"/>
  <play id="fre000672" file="GARNIERT_ETRENNES.xml"/>
  <play id="fre000673" file="GARNIERT_JOUEUSES.xml"/>
  <play id="fre000674" file="GARNIERT_MARIANNE.xml"/>
  <play id="fre000675" file="GARNIERT_PASSEDIX.xml"/>
  <play id="fre000676" file="GARNIERT_SAIGNEE.xml"/>
  <play id="fre000677" file="GARNIERT_SOEURSDELAIT.xml"/>
  <play id="fre000678" file="GARNIERT_TROISDAMIS.xml"/>
  <play id="fre000679" file="GARNIERT_VOCATIONFORCEE.xml"/>
  <play id="fre000680" file="GARNIER_BRADAMANTE.xml"/>
  <play id="fre000681" file="GENEST_JOSEPH.xml"/>
  <play id="fre000682" file="GENEST_PENELOPE.xml"/>
  <play id="fre000683" file="GENEST_ZELONIDE.xml"/>
  <play id="fre000684" file="GENLIS_AGAR.xml"/>
  <play id="fre000685" file="GENLIS_AMANTANONYME.xml"/>
  <play id="fre000686" file="GENLIS_AVEUGLEDESPA.xml"/>
  <play id="fre000687" file="GENLIS_BELLEETLABETE.xml"/>
  <play id="fre000688" file="GENLIS_BONNEMERE.xml"/>
  <play id="fre000689" file="GENLIS_CLOISON.xml"/>
  <play id="fre000690" file="GENLIS_COLOMBE.xml"/>
  <play id="fre000691" file="GENLIS_CURIEUSE.xml"/>
  <play id="fre000692" file="GENLIS_ENFANTGATE.xml"/>
  <play id="fre000693" file="GENLIS_FLACONS.xml"/>
  <play id="fre000694" file="GENLIS_ILEHEUREUSE.xml"/>
  <play id="fre000695" file="GENLIS_INTRIGUEMENSONGE.xml"/>
  <play id="fre000696" file="GENLIS_MARCHANDEDEMODES.xml"/>
  <play id="fre000697" file="GENLIS_MERERIVALE.xml"/>
  <play id="fre000698" file="GENLIS_RETOURDETOBIE.xml"/>
  <play id="fre000699" file="GENLIS_ROSIERE.xml"/>
  <play id="fre000700" file="GENLIS_RUTHNOEMI.xml"/>
  <play id="fre000701" file="GENLIS_TENDRESSEMATERNELLE.xml"/>
  <play id="fre000702" file="GENLIS_VEUVEDESAREPTE.xml"/>
  <play id="fre000703" file="GENLIS_VOYAGEUR.xml"/>
  <play id="fre000704" file="GIFFARD_MANUSCRIT.xml"/>
  <play id="fre000705" file="GILBERT_AMOURSDEDIANEETDENDYMION.xml"/>
  <play id="fre000706" file="GILBERT_RODOGUNE.xml"/>
  <play id="fre000707" file="GILBERT_SEMIRAMIS.xml"/>
  <play id="fre000708" file="GILBERT_TELEPHONTE.xml"/>
  <play id="fre000709" file="GILLET_ARTDEREGNER.xml"/>
  <play id="fre000710" file="GILLET_CAMPAGNARD.xml"/>
  <play id="fre000711" file="GILLET_DENIAISE.xml"/>
  <play id="fre000712" file="GILLET_FRANCION.xml"/>
  <play id="fre000713" file="GILLOTREGNARD_MARCHANDRIDICULE.xml"/>
  <play id="fre000714" file="GIRAUDOUX_IMPROMPTUDEPARIS.xml"/>
  <play id="fre000715" file="GIRAUDOUX_ONDINE.xml"/>
  <play id="fre000716" file="GOETSCHY_PROFESSEURDEDECLAMATION.xml"/>
  <play id="fre000717" file="GOSSE_AUTEURDANSSONMENAGE.xml"/>
  <play id="fre000718" file="GOUGES_CHERUBIN.xml"/>
  <play id="fre000719" file="GOUGES_EXCLAVAGEDESNOIRS.xml"/>
  <play id="fre000720" file="GOUGES_MOLIERENINON.xml"/>
  <play id="fre000721" file="GOULARD_AGIS.xml"/>
  <play id="fre000722" file="GOULLINET_TROISAVEUGLES.xml"/>
  <play id="fre000723" file="GOURMONT_THEODAT.xml"/>
  <play id="fre000724" file="GRAFFIGNY_PHAZA.xml"/>
  <play id="fre000725" file="GRAFFIGNY_ZIMANZENISE.xml"/>
  <play id="fre000726" file="GRANDVAL_EUNUQUE.xml"/>
  <play id="fre000727" file="GRANDVAL_LUXURIEUX.xml"/>
  <play id="fre000728" file="GRANDVAL_TEMPERAMENT.xml"/>
  <play id="fre000729" file="GRESSET_EDOUARDIII.xml"/>
  <play id="fre000730" file="GREVIN_CESAR.xml"/>
  <play id="fre000731" file="GREVIN_TRESORIERE.xml"/>
  <play id="fre000732" file="GROSCLAUDE_PECHEALALIGNE.xml"/>
  <play id="fre000733" file="GUDIN_LOTHAIRE.xml"/>
  <play id="fre000734" file="GUERINDEBOUSCAL_DOMQUIXOTE.xml"/>
  <play id="fre000735" file="GUERINDEBOUSCAL_DOMQUIXOTE2.xml"/>
  <play id="fre000736" file="GUERINDEBOUSCAL_FILSDESAVOUE.xml"/>
  <play id="fre000737" file="GUEUDEVILLE_DIALOGUESDELAHONTAN-1704.xml"/>
  <play id="fre000738" file="GUEULLETTE_AMANTCOCHEMARD.xml"/>
  <play id="fre000739" file="GUEULLETTE_AMANTPOUSSIF.xml"/>
  <play id="fre000740" file="GUEULLETTE_ARLEQUINPLUTON.xml"/>
  <play id="fre000741" file="GUEULLETTE_CARACATACA.xml"/>
  <play id="fre000742" file="GUEULLETTE_CHAPEAUDEFORTUNATUS.xml"/>
  <play id="fre000743" file="GUEULLETTE_CHASTEISABELLE.xml"/>
  <play id="fre000744" file="GUEULLETTE_CONFIANCEDESCOCUS.xml"/>
  <play id="fre000745" file="GUEULLETTE_FAUSSESENVIES.xml"/>
  <play id="fre000746" file="GUEULLETTE_ISABELLEGROSSEPARVERTU.xml"/>
  <play id="fre000747" file="GUEULLETTE_LEANDREFIACRE.xml"/>
  <play id="fre000748" file="GUEULLETTE_LEANDREHONGRE.xml"/>
  <play id="fre000749" file="GUEULLETTE_MARCHANDDEMERDE.xml"/>
  <play id="fre000750" file="GUEULLETTE_PARADE1.xml"/>
  <play id="fre000751" file="GUEULLETTE_PARADE2.xml"/>
  <play id="fre000752" file="GUIBERT_FILLESAMARIER.xml"/>
  <play id="fre000753" file="GUIMONTDELATOUCHE_IPHIGENIE.xml"/>
  <play id="fre000754" file="GUYOTDEMERVILLE_CONSENTEMENTFORCE.xml"/>
  <play id="fre000755" file="HARDY_MELEAGRE.xml"/>
  <play id="fre000756" file="HAREN_AGON.xml"/>
  <play id="fre000757" file="HARNY_PETITMAITREPROVINCE.xml"/>
  <play id="fre000758" file="HARNY_SYBILLE.xml"/>
  <play id="fre000759" file="HAUTEROCHE_COCHERSUPPOSE.xml"/>
  <play id="fre000760" file="HENAULT_MARIUSACIRTE.xml"/>
  <play id="fre000761" file="HENAULT_TEMPLEDESCHIMERES.xml"/>
  <play id="fre000762" file="HERVILLY_DOCTEURSANSPAREIL.xml"/>
  <play id="fre000763" file="HERVILLY_LAITIERE.xml"/>
  <play id="fre000764" file="HERVILLY_MAGISTER.xml"/>
  <play id="fre000765" file="HERVILLY_MALADEREEL.xml"/>
  <play id="fre000766" file="HERVILLY_MOLIEREENPRISON.xml"/>
  <play id="fre000767" file="HERVILLY_PEREETFILS.xml"/>
  <play id="fre000768" file="HERVILLY_SILENCEDANSLESRANGS.xml"/>
  <play id="fre000769" file="HERVILLY_SOUPE.xml"/>
  <play id="fre000770" file="HOFFMAN_ORIGINAL.xml"/>
  <play id="fre000771" file="HOFFMAN_PHEDRE.xml"/>
  <play id="fre000772" file="HUGO_BURGRAVES.xml" wikidata="Q3231195"/>
  <play id="fre000773" file="HUGO_HERNANI.xml" wikidata="Q1125255"/>
  <play id="fre000774" file="HUGUES_BOITEAMUSIQUE.xml"/>
  <play id="fre000775" file="HUGUES_CENDRILLON.xml"/>
  <play id="fre000776" file="HUGUES_MAISONDUDIMANCHE.xml"/>
  <play id="fre000777" file="HUGUES_NUITMOLIERE.xml"/>
  <play id="fre000778" file="HUGUES_TYL.xml"/>
  <play id="fre000779" file="HUS_INGENU.xml"/>
  <play id="fre000780" file="IMBERT_INAUGURATION.xml"/>
  <play id="fre000781" file="IMBERT_POINSINETMOLIERE.xml"/>
  <play id="fre000782" file="JACQUELINPHILIDOR_PRADON.xml"/>
  <play id="fre000783" file="JAQUELIN_SOLIMAN.xml"/>
  <play id="fre000784" file="JARRY_UBUROI.xml" wikidata="Q1215852"/>
  <play id="fre000785" file="JEANNET_MOLIEREENMENAGE.xml"/>
  <play id="fre000786" file="JODELLE_CLEOPATRE.xml"/>
  <play id="fre000787" file="JODELLE_DIDON.xml"/>
  <play id="fre000788" file="JODELLE_EUGENE.xml"/>
  <play id="fre000789" file="JOLIET_MOLIERE.xml"/>
  <play id="fre000790" file="JOLY_ADRIENNELECOUVREUR.xml"/>
  <play id="fre000791" file="JOLY_CINQMARS.xml"/>
  <play id="fre000792" file="JOLY_FOUQUETALABASTILLE.xml"/>
  <play id="fre000793" file="JOLY_MOLIERE.xml"/>
  <play id="fre000794" file="JOLY_SALOMON.xml"/>
  <play id="fre000795" file="KOLB_SOUBRETTEDEMOLIERE.xml"/>
  <play id="fre000796" file="LABAUME_MESSEDEGNIDE.xml"/>
  <play id="fre000797" file="LABICHE-JOLLY_BARONDEFOURCHEVIF.xml"/>
  <play id="fre000798" file="LABICHE-LEGOUVE_CIGALECHEZLESFOURMIS.xml"/>
  <play id="fre000799" file="LABICHE-LEROY_BRULONSVOLTAIRE.xml"/>
  <play id="fre000800" file="LABICHE-LEROY_ILESTDELAPOLICE.xml"/>
  <play id="fre000801" file="LABICHE-MICHEL_DEUXTIMIDES.xml"/>
  <play id="fre000802" file="LABICHE_COUPDERASOIR.xml"/>
  <play id="fre000803" file="LABOULLAYE-CORMON_CORNEILLEROTROU.xml"/>
  <play id="fre000804" file="LACALPRENEDE_BRADAMANTE.xml"/>
  <play id="fre000805" file="LACALPRENEDE_CLARIONTE.xml"/>
  <play id="fre000806" file="LACALPRENEDE_COMTEDESSEX.xml"/>
  <play id="fre000807" file="LACALPRENEDE_EDOUARD.xml"/>
  <play id="fre000808" file="LACALPRENEDE_ENFANTSDHERODE.xml"/>
  <play id="fre000809" file="LACALPRENEDE_HERMENEGILDE.xml"/>
  <play id="fre000810" file="LACALPRENEDE_JEANNE.xml"/>
  <play id="fre000811" file="LACALPRENEDE_MORTMITRHIDATE.xml"/>
  <play id="fre000812" file="LACALPRENEDE_PHALANTE.xml"/>
  <play id="fre000813" file="LACHAPELLE_ZAIDE.xml"/>
  <play id="fre000814" file="LACROIX_GUERRECOMIQUE.xml"/>
  <play id="fre000815" file="LAFFICHARD_ACTEURSDEPLACES.xml"/>
  <play id="fre000816" file="LAFONTAINE_ACHILLE.xml"/>
  <play id="fre000817" file="LAFONTAINE_ASTREE.xml"/>
  <play id="fre000818" file="LAFONTAINE_CLIMENE.xml"/>
  <play id="fre000819" file="LAFONTAINE_DAPHNE.xml"/>
  <play id="fre000820" file="LAFONTAINE_EUNUQUE.xml"/>
  <play id="fre000821" file="LAFONTAINE_FLORENTIN.xml"/>
  <play id="fre000822" file="LAFONTAINE_GALATEE.xml"/>
  <play id="fre000823" file="LAFONTAINE_RAGOTIN.xml"/>
  <play id="fre000824" file="LAFONTAINE_RIEURSDUBEAURICHARD.xml"/>
  <play id="fre000825" file="LAFONTLESAGE_QUERELLEDESTHEATRES.xml"/>
  <play id="fre000826" file="LAFONT_NAUFRAGE.xml"/>
  <play id="fre000827" file="LAFONT_TROISFRERESRIVAUX.xml"/>
  <play id="fre000828" file="LAFORGE_JOUEUSEDUPEE.xml"/>
  <play id="fre000829" file="LAFORGUE_NOCEDEPIERROT.xml"/>
  <play id="fre000830" file="LAFORGUE_NUITDENOCES.xml"/>
  <play id="fre000831" file="LAFOSSEM_ECOLEDELARAISON.xml"/>
  <play id="fre000832" file="LAFOSSE_MANLIUS.xml"/>
  <play id="fre000833" file="LAGRANGECHANCEL_AMASIS.xml"/>
  <play id="fre000834" file="LAGRANGECHANCEL_MELEAGRE.xml"/>
  <play id="fre000835" file="LAGRANGECHANCEL_ORESTE.xml"/>
  <play id="fre000836" file="LAHARPE_COMTEDEWARWICK.xml"/>
  <play id="fre000837" file="LAHARPE_MELANIE.xml"/>
  <play id="fre000838" file="LAHARPE_MOLIERE.xml"/>
  <play id="fre000839" file="LAHARPE_MUSESRIVALES.xml"/>
  <play id="fre000840" file="LAHARPE_PHILOCTETE.xml"/>
  <play id="fre000841" file="LAIGNELOT_AGIS.xml"/>
  <play id="fre000842" file="LAMBERT_COLLABORATION.xml"/>
  <play id="fre000843" file="LAMOTTE_AMADIS.xml"/>
  <play id="fre000844" file="LAMOTTE_CANENTE.xml"/>
  <play id="fre000845" file="LAMOTTE_CARNAVALFOLIE.xml"/>
  <play id="fre000846" file="LAMOTTE_INESDECASTRO.xml"/>
  <play id="fre000847" file="LAMOTTE_MACHABEES.xml"/>
  <play id="fre000848" file="LAMOTTE_MAGNIFIQUE.xml"/>
  <play id="fre000849" file="LAMOTTE_MATRONEDEPHESE.xml"/>
  <play id="fre000850" file="LAMOTTE_OMPHALE.xml"/>
  <play id="fre000851" file="LAMOTTE_SCANDERBERG.xml"/>
  <play id="fre000852" file="LANTIER_IMPATIENT.xml"/>
  <play id="fre000853" file="LAUJON_HEROLEANDRE.xml"/>
  <play id="fre000854" file="LAUNAY_FRANCAISCHEZLESHURONS.xml"/>
  <play id="fre000855" file="LEBEAUDESCHOSNE_ASSEMBLEE.xml"/>
  <play id="fre000856" file="LEBOULANGERCHALUSSAY_ELOMIREHYPOCONDRE.xml"/>
  <play id="fre000857" file="LECLERCQ_FOLLE.xml"/>
  <play id="fre000858" file="LECLERC_IPHIGENIE.xml"/>
  <play id="fre000859" file="LEFRANC_DIDON.xml"/>
  <play id="fre000860" file="LEGOUVEE_FLEURDETLEMCEN.xml"/>
  <play id="fre000861" file="LEGOUVE_ATTILIE.xml"/>
  <play id="fre000862" file="LEGOUVE_ETEOCLE.xml"/>
  <play id="fre000863" file="LEGOUVE_LAURENCEORZANO.xml"/>
  <play id="fre000864" file="LEGOUVE_MAFILLEETMONBIEN.xml"/>
  <play id="fre000865" file="LEGOUVE_POLIXENE.xml"/>
  <play id="fre000866" file="LEGRAND_CARTOUCHE.xml"/>
  <play id="fre000867" file="LEGRAND_FAMILLEEXTRAVAGANTE.xml"/>
  <play id="fre000868" file="LEGRAND_NOUVEAUTE.xml"/>
  <play id="fre000869" file="LEGRAND_PLUTUS.xml"/>
  <play id="fre000870" file="LEGRAND_USURIERGENTILHOMME.xml"/>
  <play id="fre000871" file="LEMERCIER_BAVARDES.xml"/>
  <play id="fre000872" file="LEMIERRE_ARTAXERCE.xml"/>
  <play id="fre000873" file="LEMIERRE_GUILLAUMETELL.xml"/>
  <play id="fre000874" file="LEMIERRE_VEUVEMALABAR.xml"/>
  <play id="fre000875" file="LENOBLE_CIBISME.xml"/>
  <play id="fre000876" file="LENOBLE_ENTRETIENSCARRONMOLIERE.xml"/>
  <play id="fre000877" file="LESAGEDORNEVAL_ILEGOUGOU.xml"/>
  <play id="fre000878" file="LESAGE_ARLEQUINMAHOMET.xml"/>
  <play id="fre000879" file="LESAGE_CRISPINRIVALDESONMAITRE.xml"/>
  <play id="fre000880" file="LESAGE_MARIAGESDECANADA.xml"/>
  <play id="fre000881" file="LESCARBOT_NEPTUNE.xml"/>
  <play id="fre000882" file="LESENNE_REVEILCORNEILLE.xml"/>
  <play id="fre000883" file="LESGUILLONSAINTYVES_PROTEGEDEMOLIERE.xml"/>
  <play id="fre000884" file="LESTOILE_BELLEESCLAVE.xml"/>
  <play id="fre000885" file="LESTOILE_INTRIGUEDESFILOUS.xml"/>
  <play id="fre000886" file="LESTOILE_MAISTREGALIMATHIAS.xml"/>
  <play id="fre000887" file="LETELLIER_DOMJUAN.xml"/>
  <play id="fre000888" file="LEVAYER_GRANDSELIM.xml"/>
  <play id="fre000889" file="LIBORLIERE_CLOISON.xml"/>
  <play id="fre000890" file="LINANT_ALZAIDE.xml"/>
  <play id="fre000891" file="LIQUIER_AMOURELECTRIQUE.xml"/>
  <play id="fre000892" file="LIQUIER_MONFUTUR.xml"/>
  <play id="fre000893" file="LONGEPIERRE_MEDEE.xml"/>
  <play id="fre000894" file="LONGHAYE_RICHELIEU.xml"/>
  <play id="fre000895" file="LONGHAYE_SOUPERDAUTEUIL.xml"/>
  <play id="fre000896" file="LOUET-LEMARCHANT_ARTISTESDESOCIETE.xml"/>
  <play id="fre000897" file="MAGNON_ARTAXERXE.xml"/>
  <play id="fre000898" file="MAGNON_JEANNEDENAPLES.xml"/>
  <play id="fre000899" file="MAGNON_JOSAPHAT.xml"/>
  <play id="fre000900" file="MAGNON_MARIAGEOROONDATE.xml"/>
  <play id="fre000901" file="MAGNON_SEJANUS.xml"/>
  <play id="fre000902" file="MAGNON_TAMERLAN.xml"/>
  <play id="fre000903" file="MAGNON_ZENOBIE.xml"/>
  <play id="fre000904" file="MAINTENON_CONVERSATIONS.xml"/>
  <play id="fre000905" file="MAIRET_ATHENAIS.xml"/>
  <play id="fre000906" file="MAIRET_ILLUSTRECORSAIRE.xml"/>
  <play id="fre000907" file="MAIRET_SOPHONISBE.xml"/>
  <play id="fre000908" file="MALEZIEU_POLICHINELLEACADEMIE.xml"/>
  <play id="fre000909" file="MARCHADIER_PLAISIR.xml"/>
  <play id="fre000910" file="MARECHAL_JUGEMENTDERNIERDESROIS.xml"/>
  <play id="fre000911" file="MARESCHALA_COURBERGERE.xml"/>
  <play id="fre000912" file="MARESCHALA_DICTATEURROMAIN.xml"/>
  <play id="fre000913" file="MARESCHALA_GENEREUSEALLEMANDE.xml"/>
  <play id="fre000914" file="MARESCHALA_GENEREUSEALLEMANDE2.xml"/>
  <play id="fre000915" file="MARESCHALA_INCONSTANCEDHYLAS.xml"/>
  <play id="fre000916" file="MARESCHALA_JUGEMENT.xml"/>
  <play id="fre000917" file="MARESCHALA_MAUZOLEE.xml"/>
  <play id="fre000918" file="MARESCHALA_RAILLEUR.xml"/>
  <play id="fre000919" file="MARESCHALA_SOEURVALEUREUSE.xml"/>
  <play id="fre000920" file="MARESCHALA_VERITABLECAPITAINEMATAMORE.xml"/>
  <play id="fre000921" file="MARIVAUX%20_ACTEURSDEBONNEFOI.xml"/>
  <play id="fre000922" file="MARIVAUX_ANNIBAL.xml"/>
  <play id="fre000923" file="MARIVAUX_ARLEQUINPOLIPARLAMOUR.xml"/>
  <play id="fre000924" file="MARIVAUX_COLONIE.xml"/>
  <play id="fre000925" file="MARIVAUX_COMMERE.xml"/>
  <play id="fre000926" file="MARIVAUX_DENOUEMENTIMPREVU.xml"/>
  <play id="fre000927" file="MARIVAUX_DISPUTE.xml"/>
  <play id="fre000928" file="MARIVAUX_DOUBLEINCONSTANCE.xml"/>
  <play id="fre000929" file="MARIVAUX_ECOLEDESMERES.xml"/>
  <play id="fre000930" file="MARIVAUX_EPREUVE.xml"/>
  <play id="fre000931" file="MARIVAUX_FAUSSESCONFIDENCES.xml"/>
  <play id="fre000932" file="MARIVAUX_FAUSSESUIVANTE.xml"/>
  <play id="fre000933" file="MARIVAUX_FELICIE.xml"/>
  <play id="fre000934" file="MARIVAUX_FEMMEFIDELE.xml"/>
  <play id="fre000935" file="MARIVAUX_HERITIERDEVILLAGE.xml"/>
  <play id="fre000936" file="MARIVAUX_HEUREUXSTRATAGEME.xml"/>
  <play id="fre000937" file="MARIVAUX_ILEDELARAISON.xml"/>
  <play id="fre000938" file="MARIVAUX_ILEDESESCLAVES.xml"/>
  <play id="fre000939" file="MARIVAUX_JEUDELAMOURETDUHASARD.xml"/>
  <play id="fre000940" file="MARIVAUX_JOIEIMPREVUE.xml"/>
  <play id="fre000941" file="MARIVAUX_LEGS.xml"/>
  <play id="fre000942" file="MARIVAUX_MEPRISE.xml"/>
  <play id="fre000943" file="MARIVAUX_MERECONFIDENTE.xml"/>
  <play id="fre000944" file="MARIVAUX_PEREPRUDENT.xml"/>
  <play id="fre000945" file="MARIVAUX_PETITMAITRECORRIGE.xml"/>
  <play id="fre000946" file="MARIVAUX_PREJUGEVAINCU.xml"/>
  <play id="fre000947" file="MARIVAUX_PRINCETRAVESTI.xml"/>
  <play id="fre000948" file="MARIVAUX_PROVINCIALE.xml"/>
  <play id="fre000949" file="MARIVAUX_REUNIONDESAMOURS.xml"/>
  <play id="fre000950" file="MARIVAUX_SECONDESURPRISEDELAMOUR.xml"/>
  <play id="fre000951" file="MARIVAUX_SERMENTSINDISCRETS.xml"/>
  <play id="fre000952" file="MARIVAUX_SINCERES.xml"/>
  <play id="fre000953" file="MARIVAUX_SURPRISEDELAMOUR.xml"/>
  <play id="fre000954" file="MARIVAUX_TRIOMPHEDELAMOUR.xml"/>
  <play id="fre000955" file="MARIVAUX_TRIOMPHEPLUTUS.xml"/>
  <play id="fre000956" file="MARMONTEL_HERCULEMOURANT.xml"/>
  <play id="fre000957" file="MARMONTEL_HURON.xml"/>
  <play id="fre000958" file="MAROLLES_AVARICIEUX.xml"/>
  <play id="fre000959" file="MATHIEU_MAGICIENNEETRANGERE.xml"/>
  <play id="fre000960" file="MAYEUR_ELEVEDELANATURE.xml"/>
  <play id="fre000961" file="MELANDRI_HALLEAUXBAISERS.xml"/>
  <play id="fre000962" file="MERCIER_DESTRUCTIONDELALIGUE.xml"/>
  <play id="fre000963" file="MERCIER_HABITANTGUADELOUPE.xml"/>
  <play id="fre000964" file="MERCIER_JENNEVAL.xml"/>
  <play id="fre000965" file="MERCIER_LIBERATEUR.xml"/>
  <play id="fre000966" file="MERCIER_TOMBEAUXDEVERONE.xml"/>
  <play id="fre000967" file="MERLE_ABASMOLIERE.xml"/>
  <play id="fre000968" file="MILLEVOYE_DIALOGUELUCIENBOILEAU.xml"/>
  <play id="fre000969" file="MILLOT_MOLIEREETSASERVANTE.xml"/>
  <play id="fre000970" file="MINIER_SONGEDEMOLIERE.xml"/>
  <play id="fre000971" file="MIRBEAU_EPIDEMIE.xml"/>
  <play id="fre000972" file="MIRBEAU_LITTERATURE.xml"/>
  <play id="fre000973" file="MOISSY_COMEDIE.xml"/>
  <play id="fre000974" file="MOISSY_DEUXMEDECINES.xml"/>
  <play id="fre000975" file="MOISSY_DUEL.xml"/>
  <play id="fre000976" file="MOISSY_GOURMANDES.xml"/>
  <play id="fre000977" file="MOISSY_GOUTE.xml"/>
  <play id="fre000978" file="MOISSY_HABITSANSGALONS.xml"/>
  <play id="fre000979" file="MOISSY_HEUREUXNATUREL.xml"/>
  <play id="fre000980" file="MOISSY_LIAISONSDANGEREUSES.xml"/>
  <play id="fre000981" file="MOISSY_MALHEURIMPREVU.xml"/>
  <play id="fre000982" file="MOISSY_MENUET.xml"/>
  <play id="fre000983" file="MOISSY_MOINEAUX.xml"/>
  <play id="fre000984" file="MOISSY_PETITEVEROLE.xml"/>
  <play id="fre000985" file="MOISSY_PETITPAYSAN.xml"/>
  <play id="fre000986" file="MOISSY_PIECEDEVERS.xml"/>
  <play id="fre000987" file="MOISSY_POCHES.xml"/>
  <play id="fre000988" file="MOISSY_POUPEE.xml"/>
  <play id="fre000989" file="MOISSY_PREJUGES.xml"/>
  <play id="fre000990" file="MOISSY_QUIPROQUO.xml"/>
  <play id="fre000991" file="MOISSY_REVENANTS.xml"/>
  <play id="fre000992" file="MOISSY_VERSION.xml"/>
  <play id="fre000993" file="MOLIERE_AMANTSMAGNIFIQUES.xml" wikidata="Q3230474"/>
  <play id="fre000994" file="MOLIERE_AMOURMEDECIN.xml"/>
  <play id="fre000995" file="MOLIERE_AMPHITRYON.xml"/>
  <play id="fre000996" file="MOLIERE_AVARE.xml"/>
  <play id="fre000997" file="MOLIERE_BOURGEOISGENTILHOMME.xml"/>
  <play id="fre000998" file="MOLIERE_COMTESSEESCARBAGNAS.xml"/>
  <play id="fre000999" file="MOLIERE_CRITIQUEECOLEDESFEMMES.xml"/>
  <play id="fre001000" file="MOLIERE_DEPITAMOUREUX.xml"/>
  <play id="fre001001" file="MOLIERE_DIVERTISSEMENTCHAMBORD.xml"/>
  <play id="fre001002" file="MOLIERE_DOMGARCIEDENAVARRE.xml"/>
  <play id="fre001003" file="MOLIERE_DOMJUAN.xml"/>
  <play id="fre001004" file="MOLIERE_ECOLEDESFEMMES.xml"/>
  <play id="fre001005" file="MOLIERE_ECOLEDESMARIS.xml"/>
  <play id="fre001006" file="MOLIERE_ETOURDI.xml"/>
  <play id="fre001007" file="MOLIERE_FACHEUX.xml"/>
  <play id="fre001008" file="MOLIERE_FEMMESSAVANTES.xml"/>
  <play id="fre001009" file="MOLIERE_FESTINDEPIERRE.xml"/>
  <play id="fre001010" file="MOLIERE_FOURBERIESDESCAPIN.xml"/>
  <play id="fre001011" file="MOLIERE_GEORGEDANDIN.xml"/>
  <play id="fre001012" file="MOLIERE_IMPROMPTUVERSAILLES.xml"/>
  <play id="fre001013" file="MOLIERE_JALOUSIEDUBARBOUILLE.xml"/>
  <play id="fre001014" file="MOLIERE_MALADEIMAGINAIRE.xml"/>
  <play id="fre001015" file="MOLIERE_MARIAGEFORCE.xml"/>
  <play id="fre001016" file="MOLIERE_MEDECINMALGRELUI.xml"/>
  <play id="fre001017" file="MOLIERE_MEDECINVOLANT.xml"/>
  <play id="fre001018" file="MOLIERE_MELICERTE.xml"/>
  <play id="fre001019" file="MOLIERE_MISANTHROPE.xml"/>
  <play id="fre001020" file="MOLIERE_MONSIEURPOURCEAUGNAC.xml"/>
  <play id="fre001021" file="MOLIERE_PRECIEUSESRIDICULES.xml"/>
  <play id="fre001022" file="MOLIERE_PRINCESSEDELIDE.xml"/>
  <play id="fre001023" file="MOLIERE_PSYCHE.xml"/>
  <play id="fre001024" file="MOLIERE_SGANARELLE.xml"/>
  <play id="fre001025" file="MOLIERE_SICILIEN.xml"/>
  <play id="fre001026" file="MOLIERE_TARTUFFE.xml"/>
  <play id="fre001027" file="MOLIERE_TARTUFFE64.xml"/>
  <play id="fre001028" file="MOLINE_INCONNUE.xml"/>
  <play id="fre001029" file="MOLINE_LEGISLATRICES.xml"/>
  <play id="fre001030" file="MONCHRETIEN_ECOSSAISE_1604.xml"/>
  <play id="fre001031" file="MONCRIF_ABDERITES.xml"/>
  <play id="fre001032" file="MONGIN_PROMENADESDEPARIS.xml"/>
  <play id="fre001033" file="MONSELET-ARENE_ILOTE.xml"/>
  <play id="fre001034" file="MONSELET_BIBLIOTHEQUE.xml"/>
  <play id="fre001035" file="MONSELET_DEUXDUMAS.xml"/>
  <play id="fre001036" file="MONSELET_ENFER.xml"/>
  <play id="fre001037" file="MONSELET_LIVRELESTE.xml"/>
  <play id="fre001038" file="MONSELET_PARLAPOSTE.xml"/>
  <play id="fre001039" file="MONSELET_PASTILLESDERICHELIEU.xml"/>
  <play id="fre001040" file="MONSELET_RHUMATISME.xml"/>
  <play id="fre001041" file="MONSELET_VOYAGEDANSMESPOCHES.xml"/>
  <play id="fre001042" file="MONS_DERNIERKLEPHTE.xml"/>
  <play id="fre001043" file="MONTALEMBERT_STATUE.xml"/>
  <play id="fre001044" file="MONTCHRETIEN_AMAN.xml"/>
  <play id="fre001045" file="MONTCHRETIEN_CARTHAGINOISE.xml"/>
  <play id="fre001046" file="MONTCHRETIEN_DAVID.xml"/>
  <play id="fre001047" file="MONTCHRETIEN_HECTOR.xml"/>
  <play id="fre001048" file="MONTCHRETIEN_LACENES.xml"/>
  <play id="fre001049" file="MONTFLEURY_IMPROMPTUCONDE.xml"/>
  <play id="fre001050" file="MONTFLEURY_LEMARIAGEDERIEN.xml"/>
  <play id="fre001051" file="MONTGAUDIER_NATALIE.xml"/>
  <play id="fre001052" file="MUSSET-AUGIER_HABITVERT.xml"/>
  <play id="fre001053" file="MUSSET_ANDREDELSARTO.xml"/>
  <play id="fre001054" file="MUSSET_ANE.xml"/>
  <play id="fre001055" file="MUSSET_BADINE.xml"/>
  <play id="fre001056" file="MUSSET_BARBERINE.xml"/>
  <play id="fre001057" file="MUSSET_CAPRICE.xml"/>
  <play id="fre001058" file="MUSSET_CAPRICES.xml"/>
  <play id="fre001059" file="MUSSET_CARMOSINE.xml"/>
  <play id="fre001060" file="MUSSET_ILNEFAUTJURERDERIEN.xml" slug="musset-il-ne-faut-jurer-de-rien" print="1836" premiere="1848" wikidata="Q3148527"/>
  <play id="fre001061" file="MUSSET_LORENZACCIO.xml"/>
  <play id="fre001062" file="MUSSET_NUITVENITIENNE.xml"/>
  <play id="fre001063" file="NADAL_ANTIOCHUS.xml"/>
  <play id="fre001064" file="NADAL_EPOUSEDUCANTIQUE.xml"/>
  <play id="fre001065" file="NADAL_ESTHER.xml"/>
  <play id="fre001066" file="NADAL_HERODE.xml"/>
  <play id="fre001067" file="NADAL_MARIAMNE.xml"/>
  <play id="fre001068" file="NADAL_OSARPHISMOISE.xml"/>
  <play id="fre001069" file="NADAL_PARADISTERRESTRE.xml"/>
  <play id="fre001070" file="NADAL_SAUL.xml"/>
  <play id="fre001071" file="NADAUD_DOUBLEAVEU.xml"/>
  <play id="fre001072" file="NADAUD_EXAMEN.xml"/>
  <play id="fre001073" file="NADAUD_ORAISONFUNEBRE.xml"/>
  <play id="fre001074" file="NADAUD_PROVERBEMANQUE.xml"/>
  <play id="fre001075" file="NERICAULT_GLORIEUX.xml"/>
  <play id="fre001076" file="NIVELLE_ECOLEDESAMIS.xml"/>
  <play id="fre001077" file="NIVELLE_ECOLEMERES.xml"/>
  <play id="fre001078" file="NIVELLE_FAUSSEANTIPATHIE.xml"/>
  <play id="fre001079" file="NIVELLE_GOUVERNANTE.xml"/>
  <play id="fre001080" file="NIVELLE_PREJUGEALAMODE.xml"/>
  <play id="fre001081" file="NIZAS_SAUVAGEENFRANCE.xml"/>
  <play id="fre001082" file="NORMAND_CLAQUEURS.xml"/>
  <play id="fre001083" file="NORMAND_TENTATIONSDANTOINE.xml"/>
  <play id="fre001084" file="ONHET_AUXAVANTSPOSTES.xml"/>
  <play id="fre001085" file="ORMOY_ZELMIS.xml"/>
  <play id="fre001086" file="OUVILLE_ABSENTCHEZSOI.xml"/>
  <play id="fre001087" file="OUVILLE_FAUSSESVERITES.xml"/>
  <play id="fre001088" file="OUVILLE_SOUPCONS.xml"/>
  <play id="fre001089" file="OZICOURT_BELIZAIRE.xml"/>
  <play id="fre001090" file="OZICOURT_ROMEOJULIETTE.xml"/>
  <play id="fre001091" file="PACARONI_BAJAZETPREMIER.xml"/>
  <play id="fre001092" file="PAGES_MOLIEREAPEZENAS.xml"/>
  <play id="fre001093" file="PAIN-RIOU_CHOUANS.xml"/>
  <play id="fre001094" file="PAIN_APPARTEMENTALOUER.xml"/>
  <play id="fre001095" file="PALISSOT_BARBIERDEBAGDAD.xml"/>
  <play id="fre001096" file="PALISSOT_CERCLE.xml"/>
  <play id="fre001097" file="PALISSOT_CRITIQUETRAGEDIECHARLESIX.xml"/>
  <play id="fre001098" file="PALISSOT_NINUS.xml"/>
  <play id="fre001099" file="PALISSOT_PHILOSOPHES.xml"/>
  <play id="fre001100" file="PALISSOT_TUTEURS.xml"/>
  <play id="fre001101" file="PANARD_RIEN.xml"/>
  <play id="fre001102" file="PATRAT_HEUREUSEERREUR.xml"/>
  <play id="fre001103" file="PATRAT_VENGEANCE.xml"/>
  <play id="fre001104" file="PECHANTRE_GETA.xml"/>
  <play id="fre001105" file="PELLEGRIN_TIBERE.xml"/>
  <play id="fre001106" file="PELLET-DESBARREAUX_MOLIEREATOULOUSE.xml"/>
  <play id="fre001107" file="PERIN_CAMILLEDESMOULINS.xml"/>
  <play id="fre001108" file="PESSELIER_ESOPEAUPARNASSE.xml"/>
  <play id="fre001109" file="PG_ALAMONACO.xml"/>
  <play id="fre001110" file="PG_AMOUR.xml"/>
  <play id="fre001111" file="PG_CARNAVALDUBARON.xml"/>
  <play id="fre001112" file="PG_FAUSSEINVITE.xml"/>
  <play id="fre001113" file="PG_THESEE.xml"/>
  <play id="fre001114" file="PIC_ARICIE.xml"/>
  <play id="fre001115" file="PIFTEAU_MOLIEREENVOYAGE.xml"/>
  <play id="fre001116" file="PIIS_CASSANDREASTROLOGUE.xml"/>
  <play id="fre001117" file="PIRON_ARLEQUINDECALION.xml"/>
  <play id="fre001118" file="PIRON_ECOLEPERES.xml"/>
  <play id="fre001119" file="PIRON_FAUSSEALARME.xml"/>
  <play id="fre001120" file="PIRON_GUSTAVEWASA.xml"/>
  <play id="fre001121" file="PIRON_METROMANIE.xml"/>
  <play id="fre001122" file="PIRON_NOUVELLEMESSALINE.xml"/>
  <play id="fre001123" file="PIRON_VASTA.xml"/>
  <play id="fre001124" file="PIROUETTE_JEUNEHOMMEBLEME.xml"/>
  <play id="fre001125" file="PIXERECOURT_VICTOR.xml"/>
  <play id="fre001126" file="PLANCHER_VERREDEAU.xml"/>
  <play id="fre001127" file="PLAUTE_AMPHITRYON.xml"/>
  <play id="fre001128" file="PLAUTE_AULULAIRE.xml"/>
  <play id="fre001129" file="PLAUTE_CASINA.xml"/>
  <play id="fre001130" file="POINSINET_AJAX.xml"/>
  <play id="fre001131" file="POINSINET_CERCLE.xml"/>
  <play id="fre001132" file="POINSINET_FRAMACONNES.xml"/>
  <play id="fre001133" file="POINSINET_PHILOSOPHESDEBOIS.xml"/>
  <play id="fre001134" file="POISSON_ACTRICENOUVELLE.xml"/>
  <play id="fre001135" file="POISSON_AMOURSECRET.xml"/>
  <play id="fre001136" file="POISSON_BOITEDEPANDORE.xml"/>
  <play id="fre001137" file="POISSON_HOLANDEMALADE.xml"/>
  <play id="fre001138" file="POISSON_SOTVENGE.xml"/>
  <play id="fre001139" file="POMPIGNY_NOEUDDAMOUR.xml"/>
  <play id="fre001140" file="PONSART_MOLIEREAVIENNE.xml"/>
  <play id="fre001141" file="POULHARIEZ_TACITURNE.xml"/>
  <play id="fre001142" file="POUSSETDEMONTAUBAN_FELICIE.xml"/>
  <play id="fre001143" file="POUSSETDEMONTAUBAN_ZENOBIE.xml"/>
  <play id="fre001144" file="PRADEL_MOLIEREAVIGNON.xml"/>
  <play id="fre001145" file="PRADEL_TRAITDEMOLIERE.xml"/>
  <play id="fre001146" file="PRADE_ARSACE.xml"/>
  <play id="fre001147" file="PRADON_MORTDEBAJAZET.xml"/>
  <play id="fre001148" file="PRADON_PHEDRE.xml"/>
  <play id="fre001149" file="PRADON_REGULUS.xml"/>
  <play id="fre001150" file="PRADON_SCIPION.xml"/>
  <play id="fre001151" file="PRADON_STATIRA.xml"/>
  <play id="fre001152" file="PUGETDELASERRE_CLIMENE.xml"/>
  <play id="fre001153" file="PUGETDELASERRE_MARTYRESAINTECATHERINE.xml"/>
  <play id="fre001154" file="PUGETDELASERRE_PANDOSTE_I.xml"/>
  <play id="fre001155" file="PUGETDELASERRE_PANDOSTE_II.xml"/>
  <play id="fre001156" file="PUGETDELASERRE_SACDECARTHAGE.xml"/>
  <play id="fre001157" file="PUGETDELASERRE_THESEE.xml"/>
  <play id="fre001158" file="PUGETDELASERRE_THOMASMORUS.xml"/>
  <play id="fre001159" file="PURE_DEROUTEDESPRECIEUSES.xml"/>
  <play id="fre001160" file="PURE_OSTORIUS.xml"/>
  <play id="fre001161" file="QUINAULT_AGRIPPA.xml"/>
  <play id="fre001162" file="QUINAULT_ALCESTE.xml"/>
  <play id="fre001163" file="QUINAULT_AMADIS.xml"/>
  <play id="fre001164" file="QUINAULT_AMALASONTE.xml"/>
  <play id="fre001165" file="QUINAULT_ARMIDE.xml"/>
  <play id="fre001166" file="QUINAULT_ATYS.xml"/>
  <play id="fre001167" file="QUINAULT_BELLEROPHON.xml"/>
  <play id="fre001168" file="QUINAULT_CADMUSHERMIONE.xml"/>
  <play id="fre001169" file="QUINAULT_COMEDIESANSCOMEDIE.xml"/>
  <play id="fre001170" file="QUINAULT_COUPSDELAMOUR.xml"/>
  <play id="fre001171" file="QUINAULT_DOCTEURDEVERRE.xml"/>
  <play id="fre001172" file="QUINAULT_FANTOMEAMOUREUX.xml"/>
  <play id="fre001173" file="QUINAULT_FETESAMOURBACCHUS.xml"/>
  <play id="fre001174" file="QUINAULT_GENEREUSEINGRATITUDE.xml"/>
  <play id="fre001175" file="QUINAULT_GROTTE.xml"/>
  <play id="fre001176" file="QUINAULT_ISIS.xml"/>
  <play id="fre001177" file="QUINAULT_MERECOQUETTE.xml"/>
  <play id="fre001178" file="QUINAULT_PERSEE.xml"/>
  <play id="fre001179" file="QUINAULT_PROSERPINE.xml"/>
  <play id="fre001180" file="QUINAULT_ROLAND.xml"/>
  <play id="fre001181" file="QUINAULT_STRATONICE.xml"/>
  <play id="fre001182" file="QUINAULT_TEMPLEDELAPAIX.xml"/>
  <play id="fre001183" file="QUINAULT_THESEE.xml"/>
  <play id="fre001184" file="RACINE_ALEXANDRE.xml" slug="racine-alexandre-le-grand" wikidata="Q2834224"/>
  <play id="fre001185" file="RACINE_ALEXANDRE66.xml" slug="racine-alexandre-le-grand-66" wikidata="Q2834224"/>
  <play id="fre001186" file="RACINE_ANDROMAQUE.xml" slug="racine-andromaque" wikidata="Q512807"/>
  <play id="fre001187" file="RACINE_ANDROMAQUE68.xml" slug="racine-andromaque-68" wikidata="Q512807"/>
  <play id="fre001188" file="RACINE_ATHALIE.xml" slug="racine-athalie" wikidata="Q754687"/>
  <play id="fre001189" file="RACINE_BAJAZET.xml" slug="racine-bajazet" wikidata="Q788676"/>
  <play id="fre001190" file="RACINE_BERENICE.xml" slug="racine-berenice" wikidata="Q793366"/>
  <play id="fre001191" file="RACINE_BRITANNICUS.xml" slug="racine-britannicus" wikidata="Q1196012"/>
  <play id="fre001192" file="RACINE_ESTHER.xml" slug="racine-esther" wikidata="Q746818"/>
  <play id="fre001193" file="RACINE_IPHIGENIE.xml" slug="racine-iphigenie" wikidata="Q903424"/>
  <play id="fre001194" file="RACINE_MITHRIDATE.xml" slug="racine-mithridate" wikidata="Q740134"/>
  <play id="fre001195" file="RACINE_PHEDRE.xml" slug="racine-phedre" wikidata="Q969098"/>
  <play id="fre001196" file="RACINE_PHEDRE77.xml" slug="racine-phedre-et-hippolyte-77" wikidata="Q969098"/>
  <play id="fre001197" file="RACINE_PLAIDEURS.xml" slug="racine-les-plaideurs" wikidata="Q583392"/>
  <play id="fre001198" file="RACINE_PLAIDEURS69.xml" slug="racine-les-plaudeurs-69" wikidata="Q583392"/>
  <play id="fre001199" file="RACINE_THEBAIDE.xml" slug="racine-la-thebaide" wikidata="Q3213141"/>
  <play id="fre001200" file="RACINE_THEBAIDE64.xml" slug="racine-la-thebaide-64" wikidata="Q3213141"/>
  <play id="fre001201" file="RAYSSIGUIER_PALINICE.xml" slug="rayssiguier-palinice-circeine-et-florice"/>
  <play id="fre001202" file="REGNARD_ARLEQUINAUXENFERS.xml"/>
  <play id="fre001203" file="REGNARD_ARLEQUINBONNESFORTUNES.xml"/>
  <play id="fre001204" file="REGNARD_ATTENDEZSOUSLORME.xml"/>
  <play id="fre001205" file="REGNARD_BAL.xml"/>
  <play id="fre001206" file="REGNARD_CARNAVALDEVENISE.xml"/>
  <play id="fre001207" file="REGNARD_COQUETTE.xml"/>
  <play id="fre001208" file="REGNARD_DEMOCRITE.xml"/>
  <play id="fre001209" file="REGNARD_DISTRAIT.xml"/>
  <play id="fre001210" file="REGNARD_DIVORCE.xml"/>
  <play id="fre001211" file="REGNARD_FILLESERRANTES.xml"/>
  <play id="fre001212" file="REGNARD_FOLIESAMOUREUSES.xml"/>
  <play id="fre001213" file="REGNARD_HOMMEBONNEFORTUNECRITIQUE.xml"/>
  <play id="fre001214" file="REGNARD_JOUEUR.xml"/>
  <play id="fre001215" file="REGNARD_LEGATAIRE.xml"/>
  <play id="fre001216" file="REGNARD_LEGATAIRECRITIQUE.xml"/>
  <play id="fre001217" file="REGNARD_MENECHMES.xml"/>
  <play id="fre001218" file="REGNARD_RETOURIMPREVU.xml"/>
  <play id="fre001219" file="REGNARD_SAPOR.xml"/>
  <play id="fre001220" file="REGNARD_SERENADE.xml"/>
  <play id="fre001221" file="REGNARD_SOUHAITS.xml"/>
  <play id="fre001222" file="REGNARD_VENDANGES.xml"/>
  <play id="fre001223" file="RENARD_MAITRESSE.xml"/>
  <play id="fre001224" file="RENARD_PLAISIRDEROMPRE.xml"/>
  <play id="fre001225" file="RESTIF_JUGEMENTDEPARIS.xml"/>
  <play id="fre001226" file="RICCOBONI-RICCOBONI-ROMAGNESI_ECHODUPUBLIC.xml"/>
  <play id="fre001227" file="RICCOBONIROMAGNESI_COMPLIMENTS.xml"/>
  <play id="fre001228" file="ROBINET_PANEGYRIQUEECOLEDESFEMMES.xml"/>
  <play id="fre001229" file="ROCHON_HEUREUSEMENT.xml"/>
  <play id="fre001230" file="ROGER_AUTEURCAPITATION.xml"/>
  <play id="fre001231" file="ROMAGNESIRICCOBONI_SAUVAGES.xml"/>
  <play id="fre001232" file="ROMAGNESI_RANCUNE.xml"/>
  <play id="fre001233" file="RONSIN_ARETAPHILE.xml"/>
  <play id="fre001234" file="RONSIN_LIGUESDESFANATIQUES.xml"/>
  <play id="fre001235" file="ROSIMOND_AVOCATSAVETIER.xml"/>
  <play id="fre001236" file="ROSIMOND_FESTINDEPIERRE.xml"/>
  <play id="fre001237" file="ROTROU_AGESILAN.xml"/>
  <play id="fre001238" file="ROTROU_AMARILLIS.xml"/>
  <play id="fre001239" file="ROTROU_AMELIE.xml"/>
  <play id="fre001240" file="ROTROU_ANTIGONE.xml"/>
  <play id="fre001241" file="ROTROU_BAGUEDELOUBLI.xml"/>
  <play id="fre001242" file="ROTROU_BELISAIRE.xml"/>
  <play id="fre001243" file="ROTROU_BELLEALPHREDE.xml"/>
  <play id="fre001244" file="ROTROU_CAPTIFS.xml"/>
  <play id="fre001245" file="ROTROU_CELIANE.xml"/>
  <play id="fre001246" file="ROTROU_CLEAGENOR.xml"/>
  <play id="fre001247" file="ROTROU_COSROES.xml"/>
  <play id="fre001248" file="ROTROU_DEUXPUCELLES.xml"/>
  <play id="fre001249" file="ROTROU_DOMBERNARDDECABRERE.xml"/>
  <play id="fre001250" file="ROTROU_HERCULEMOURANT.xml"/>
  <play id="fre001251" file="ROTROU_IPHIGENIE.xml"/>
  <play id="fre001252" file="ROTROU_SAINTGENEST.xml"/>
  <play id="fre001253" file="ROTROU_SOSIES.xml"/>
  <play id="fre001254" file="ROTROU_VENCESLAS.xml"/>
  <play id="fre001255" file="ROUGEMONT_DISCOURSDERENTREE.xml"/>
  <play id="fre001256" file="ROUSSEAUJB_CAFE.xml"/>
  <play id="fre001257" file="ROUSSEAUJB_CEINTUREMAGIQUE.xml"/>
  <play id="fre001258" file="ROUSSEAUJB_JASON.xml"/>
  <play id="fre001259" file="ROUSSEAUP_MORTDEBUCEPHALE.xml"/>
  <play id="fre001260" file="ROUSSEAU_DEVINDUVILLAGE.xml"/>
  <play id="fre001261" file="ROUSSEAU_ENGAGEMENTTEMERAIRE.xml"/>
  <play id="fre001262" file="ROUSSEAU_MUSESGALANTES.xml"/>
  <play id="fre001263" file="ROUSSEAU_NARCISSE.xml"/>
  <play id="fre001264" file="ROUSSEAU_PRISONNIERSDEGUERRE.xml"/>
  <play id="fre001265" file="ROY_COMPLIMENT14MARS1750.xml"/>
  <play id="fre001266" file="ROY_COMPLIMENT7AVRIL1750.xml"/>
  <play id="fre001267" file="SACY_AGNESSOREL.xml"/>
  <play id="fre001268" file="SACY_AMOURPLATONIQUE.xml"/>
  <play id="fre001269" file="SACY_BAVARD.xml"/>
  <play id="fre001270" file="SACY_BENEFICE.xml"/>
  <play id="fre001271" file="SACY_BOISROSE.xml"/>
  <play id="fre001272" file="SACY_CONTENTEMENT.xml"/>
  <play id="fre001273" file="SACY_DEFENSE.xml"/>
  <play id="fre001274" file="SACY_DENYS.xml"/>
  <play id="fre001275" file="SACY_FATDEPROVINCE.xml"/>
  <play id="fre001276" file="SACY_FAUSSEPAYSANNE.xml"/>
  <play id="fre001277" file="SACY_GASCONAPARIS.xml"/>
  <play id="fre001278" file="SACY_GASCONJOUE.xml"/>
  <play id="fre001279" file="SACY_HARANGUE.xml"/>
  <play id="fre001280" file="SACY_IMPROMPTU.xml"/>
  <play id="fre001281" file="SACY_LOIS.xml"/>
  <play id="fre001282" file="SACY_MEDISANCE.xml"/>
  <play id="fre001283" file="SACY_MEPRISE.xml"/>
  <play id="fre001284" file="SACY_MERLINPERCEPTEUR.xml"/>
  <play id="fre001285" file="SACY_MODESTIE.xml"/>
  <play id="fre001286" file="SACY_MORTSVIVANTS.xml"/>
  <play id="fre001287" file="SACY_MYSTERIEUX.xml"/>
  <play id="fre001288" file="SACY_NOBLESSE.xml"/>
  <play id="fre001289" file="SACY_NOUVELLISTES.xml"/>
  <play id="fre001290" file="SACY_QUINE.xml"/>
  <play id="fre001291" file="SACY_REPETITION.xml"/>
  <play id="fre001292" file="SACY_RETOURDISTRAIT.xml"/>
  <play id="fre001293" file="SACY_RIVALITE.xml"/>
  <play id="fre001294" file="SACY_SECRETAIRE.xml"/>
  <play id="fre001295" file="SACY_SERPETTEMAGIQUE.xml"/>
  <play id="fre001296" file="SACY_SONGES.xml"/>
  <play id="fre001297" file="SACY_SYMPATHIE.xml"/>
  <play id="fre001298" file="SACY_TESTAMENT.xml"/>
  <play id="fre001299" file="SACY_TROISIVROGNES.xml"/>
  <play id="fre001300" file="SACY_VANITE.xml"/>
  <play id="fre001301" file="SACY_VIVELAVIE.xml"/>
  <play id="fre001302" file="SAINT-FOIX_CABALE.xml"/>
  <play id="fre001303" file="SAINT-FOIX_COLONIE.xml"/>
  <play id="fre001304" file="SAINT-FOIX_HOMMES.xml"/>
  <play id="fre001305" file="SAINT-FOIX_ILESAUVAGE.xml"/>
  <play id="fre001306" file="SAINT-FOIX_ORACLE.xml"/>
  <play id="fre001307" file="SAINT-GILLES_DIALOGUE.xml"/>
  <play id="fre001308" file="SAINT-GILLES_FEINTEHEUREUSE.xml"/>
  <play id="fre001309" file="SAINT-GILLES_FIEVREPALMERIN.xml"/>
  <play id="fre001310" file="SAINT-JUST_PETITEMAISON.xml"/>
  <play id="fre001311" file="SAINT-ROMAN_DIALOGUE.xml"/>
  <play id="fre001312" file="SAINTAIGNAN_MARTYREMARIEANTOINETTE.xml"/>
  <play id="fre001313" file="SAINTAIGNAN_MORTLOUISXVI.xml"/>
  <play id="fre001314" file="SAINTEVREMOND_COMEDIEDESACADEMICIENS.xml"/>
  <play id="fre001315" file="SAINTPRIEST_POTAUNOIRPOTAUXROSES.xml"/>
  <play id="fre001316" file="SALLEBRAY_BELLEEGYPTIENNE.xml"/>
  <play id="fre001317" file="SAND_ALDOLERIMEUR.xml"/>
  <play id="fre001318" file="SAND_MOLIERE.xml"/>
  <play id="fre001319" file="SAND_ROIATTEND.xml"/>
  <play id="fre001320" file="SAURIN_ANGLOMANE.xml"/>
  <play id="fre001321" file="SAURIN_BEVERLEI.xml"/>
  <play id="fre001322" file="SAURIN_BLANCHEETGUISCARD.xml"/>
  <play id="fre001323" file="SAURIN_MARIAGEDEJULIE.xml"/>
  <play id="fre001324" file="SAURIN_MOEURSDUTEMPS.xml"/>
  <play id="fre001325" file="SAURIN_SPARTACUS.xml"/>
  <play id="fre001326" file="SCARRON_BOUTADESMATAMORE.xml"/>
  <play id="fre001327" file="SCARRON_DOMJAPHETDARMENIE.xml"/>
  <play id="fre001328" file="SCARRON_ECOLIERDESALAMANQUE.xml"/>
  <play id="fre001329" file="SCARRON_FAUSSEAPPARENCE.xml"/>
  <play id="fre001330" file="SCARRON_GARDIENDESOIMEME.xml"/>
  <play id="fre001331" file="SCARRON_HERITIERRIDICULE.xml"/>
  <play id="fre001332" file="SCARRON_JODELET.xml"/>
  <play id="fre001333" file="SCARRON_JODELETDUELISTE.xml"/>
  <play id="fre001334" file="SCARRON_MARQUISRIDICULE.xml"/>
  <play id="fre001335" file="SCARRON_PRINCECORSAIRE.xml"/>
  <play id="fre001336" file="SCHELANDRE_TYRSIDON_I.xml"/>
  <play id="fre001337" file="SCHELANDRE_TYRSIDON_II.xml"/>
  <play id="fre001338" file="SCRIBE_CONVERSION.xml"/>
  <play id="fre001339" file="SCRIBE_JEUNEDOCTEUR.xml"/>
  <play id="fre001340" file="SCRIBE_MINISTRESOUSLOUISXV.xml"/>
  <play id="fre001341" file="SCRIBE_POTEMKIN.xml"/>
  <play id="fre001342" file="SCRIBE_TETEATETE.xml"/>
  <play id="fre001343" file="SCUDERY_AMOURTYRAN.xml"/>
  <play id="fre001344" file="SCUDERY_ARMINIUS.xml"/>
  <play id="fre001345" file="SCUDERY_COMEDIEDESCOMEDIENS.xml"/>
  <play id="fre001346" file="SCUDERY_EUDOXE.xml"/>
  <play id="fre001347" file="SCUDERY_FILSSUPPOSE.xml"/>
  <play id="fre001348" file="SCUDERY_LIGDAMONELIDIAS.xml"/>
  <play id="fre001349" file="SCUDERY_MORTDECESAR.xml"/>
  <play id="fre001350" file="SCUDERY_ORANTE.xml"/>
  <play id="fre001351" file="SCUDERY_PRINCEDEGUISE.xml"/>
  <play id="fre001352" file="SCUDERY_VASSALGENEREUX.xml"/>
  <play id="fre001353" file="SEDAINE_DEFAUTSSUPPOSES.xml"/>
  <play id="fre001354" file="SEDAINE_MANTEAUECARLATE.xml"/>
  <play id="fre001355" file="SEDAINE_RICHARD.xml"/>
  <play id="fre001356" file="SEGUR_FOU.xml"/>
  <play id="fre001357" file="SENEQUE_AGAMEMNON.xml"/>
  <play id="fre001358" file="SENEQUE_MEDEE.xml"/>
  <play id="fre001359" file="SIVRY_AFFAIREDHONNEUR.xml"/>
  <play id="fre001360" file="SIVRY_INDECISION.xml"/>
  <play id="fre001361" file="SOMAIZE_PRECIEUSESRIDICULES.xml"/>
  <play id="fre001362" file="SOMAIZE_PROCESPRECIEUSES.xml"/>
  <play id="fre001363" file="SOMAIZE_VERITABLESPRECIEUSES.xml"/>
  <play id="fre001364" file="SOMMERIVE_BAJAZET.xml"/>
  <play id="fre001365" file="SOPHOCLE_AJAX.xml"/>
  <play id="fre001366" file="SOPHOCLE_ANTIGONE.xml"/>
  <play id="fre001367" file="SOPHOCLE_ELECTRE.xml"/>
  <play id="fre001368" file="SOPHOCLE_OEDIPEACOLONE.xml"/>
  <play id="fre001369" file="SOPHOCLE_OEDIPEROI.xml"/>
  <play id="fre001370" file="SOPHOCLE_PHILOCTETE.xml"/>
  <play id="fre001371" file="SOPHOCLE_TRACHINIENNES.xml"/>
  <play id="fre001372" file="SORET_CECILIADE.xml"/>
  <play id="fre001373" file="STAEL_AGAR.xml"/>
  <play id="fre001374" file="STAEL_SIGNORAFANTASTICI.xml"/>
  <play id="fre001375" file="SUBLIGNY_FOLLEQUERELLE.xml"/>
  <play id="fre001376" file="TACONET_ECOSSEUSES.xml"/>
  <play id="fre001377" file="TACONET_EPOUXPARCHICANE.xml"/>
  <play id="fre001378" file="TACONET_NOSTRADAMUS.xml"/>
  <play id="fre001379" file="TANEVOT_ADAMETEVE.xml"/>
  <play id="fre001380" file="THIBOUVILLE_THELAMIRE.xml"/>
  <play id="fre001381" file="TRIMOUILLAT_ATROISPAS.xml"/>
  <play id="fre001382" file="TRISTAN_MARIANE.xml"/>
  <play id="fre001383" file="TRISTAN_MORTDECHRISPE.xml"/>
  <play id="fre001384" file="TRISTAN_MORTSENEQUE.xml"/>
  <play id="fre001385" file="TRISTAN_OSMAN.xml"/>
  <play id="fre001386" file="TRISTAN_PARASITE.xml"/>
  <play id="fre001387" file="TURNEBE_CONTENTS.xml"/>
  <play id="fre001388" file="URFE_SYLVANIRE.xml"/>
  <play id="fre001389" file="VADE_CANADIENNE.xml"/>
  <play id="fre001390" file="VADE_IMPROMPTUDUCOEUR.xml"/>
  <play id="fre001391" file="VADE_POIRIER.xml"/>
  <play id="fre001392" file="VADE_VEUVEINDECISE.xml"/>
  <play id="fre001393" file="VALLEE_FIDELEESCLAVE.xml"/>
  <play id="fre001394" file="VALLEE_FORTEROMAINE.xml"/>
  <play id="fre001395" file="VANDER-BURCH_PROCESRACINECONCILIATEUR.xml"/>
  <play id="fre001396" file="VERCONSIN_RETOURDEBRUXELLES.xml"/>
  <play id="fre001397" file="VERCONSIN_RIDEAU.xml"/>
  <play id="fre001398" file="VESSAIRE_CAQUIRE.xml"/>
  <play id="fre001399" file="VIAU_PASIPHAE.xml"/>
  <play id="fre001400" file="VIAU_PYRAME.xml"/>
  <play id="fre001401" file="VIERNE_MOLIEREENFANT.xml"/>
  <play id="fre001402" file="VIGE_OTHELLO.xml"/>
  <play id="fre001403" file="VILLARD_CLOWN.xml"/>
  <play id="fre001404" file="VILLIERSDELISLEADAM_CHAPEAUCHINOIS.xml"/>
  <play id="fre001405" file="VILLIERS_CRITIQUEDUTARTUFFE.xml"/>
  <play id="fre001406" file="VILLIERS_FESTINDEPIERRE.xml"/>
  <play id="fre001407" file="VOISENON_HILASETZELIS.xml"/>
  <play id="fre001408" file="VOLTAIRE_ADELAIDE.xml"/>
  <play id="fre001409" file="VOLTAIRE_AGATHOCLE.xml"/>
  <play id="fre001410" file="VOLTAIRE_ALZIRE.xml"/>
  <play id="fre001411" file="VOLTAIRE_BARONDOTRANTE.xml"/>
  <play id="fre001412" file="VOLTAIRE_BRUTUS.xml"/>
  <play id="fre001413" file="VOLTAIRE_CAFE.xml"/>
  <play id="fre001414" file="VOLTAIRE_CHARLOT.xml"/>
  <play id="fre001415" file="VOLTAIRE_COMTEDEBOURSOUFLE.xml"/>
  <play id="fre001416" file="VOLTAIRE_DEPOSITAIRE.xml"/>
  <play id="fre001417" file="VOLTAIRE_DEUXTONNEAUX.xml"/>
  <play id="fre001418" file="VOLTAIRE_DROITDUSEIGNEUR.xml"/>
  <play id="fre001419" file="VOLTAIRE_DUCDALENCON.xml"/>
  <play id="fre001420" file="VOLTAIRE_ENFANTPRODIGUE.xml"/>
  <play id="fre001421" file="VOLTAIRE_ENVIEUX.xml"/>
  <play id="fre001422" file="VOLTAIRE_FANATISME.xml"/>
  <play id="fre001423" file="VOLTAIRE_FEMMEQUIARAISON.xml"/>
  <play id="fre001424" file="VOLTAIRE_FETEDEBELLEBAT.xml"/>
  <play id="fre001425" file="VOLTAIRE_GUEBRES.xml"/>
  <play id="fre001426" file="VOLTAIRE_HOTEHOTESSE.xml"/>
  <play id="fre001427" file="VOLTAIRE_INDISCRET.xml"/>
  <play id="fre001428" file="VOLTAIRE_IRENE.xml"/>
  <play id="fre001429" file="VOLTAIRE_LOISDEMINOS.xml"/>
  <play id="fre001430" file="VOLTAIRE_MARIAMNE.xml"/>
  <play id="fre001431" file="VOLTAIRE_MEROPE.xml"/>
  <play id="fre001432" file="VOLTAIRE_MORTDECESAR.xml"/>
  <play id="fre001433" file="VOLTAIRE_NANINE.xml"/>
  <play id="fre001434" file="VOLTAIRE_OEDIPE_V.xml"/>
  <play id="fre001435" file="VOLTAIRE_OLYMPIE.xml"/>
  <play id="fre001436" file="VOLTAIRE_ORESTE.xml"/>
  <play id="fre001437" file="VOLTAIRE_ORIGINAUX.xml"/>
  <play id="fre001438" file="VOLTAIRE_ORPHELINDELACHINE.xml"/>
  <play id="fre001439" file="VOLTAIRE_PANDORE.xml"/>
  <play id="fre001440" file="VOLTAIRE_PELOPIDES.xml"/>
  <play id="fre001441" file="VOLTAIRE_ROMESAUVEE.xml"/>
  <play id="fre001442" file="VOLTAIRE_SAMSON.xml"/>
  <play id="fre001443" file="VOLTAIRE_SAUL.xml"/>
  <play id="fre001444" file="VOLTAIRE_SCYTHES.xml"/>
  <play id="fre001445" file="VOLTAIRE_SEMIRAMIS.xml"/>
  <play id="fre001446" file="VOLTAIRE_SOCRATE.xml"/>
  <play id="fre001447" file="VOLTAIRE_SOPHONISBE.xml"/>
  <play id="fre001448" file="VOLTAIRE_TANCREDE.xml"/>
  <play id="fre001449" file="VOLTAIRE_TANISZELIDE.xml"/>
  <play id="fre001450" file="VOLTAIRE_ZAIRE.xml"/>
  <play id="fre001451" file="VOLTAIRE_ZULIME.xml"/>
  <play id="fre001452" file="VONDREBECK-ALARD_FORCESDELAMOUR.xml"/>
  <play id="fre001453" file="BRUEYS_EMPIRIQUES.xml"/>
  <play id="fre001454" file="CAMPISTRON_TIRIDATE.xml"/>
  <play id="fre001455" file="FATOUVILLE_ARLEQUINEMPEREURDANSLALUNE.xml"/>
  <play id="fre001456" file="FATOUVILLE_GRAPINIAN.xml"/>
  <play id="fre001457" file="LATHUILERIE_CRISPINBELESPRIT.xml"/>
  <play id="fre001458" file="LATHUILERIE_HERCULE.xml"/>
  <play id="fre001459" file="LATHUILERIE_SOLIMAN.xml"/>
  <play id="fre001460" file="RAISIN_MERLINGASCON.xml"/>
  <play id="fre001461" file="ABOUT_RISETTE.xml"/>
  <play id="fre001462" file="ANSEAUME_TABLEAUPARLANT.xml"/>
  <play id="fre001463" file="BECQUE_CORBEAUX.xml"/>
  <play id="fre001464" file="BECQUE_ENLEVEMENT.xml"/>
  <play id="fre001465" file="BLEMOND_MOLIEREAUTEUIL.xml"/>
  <play id="fre001466" file="LEMIERRE_IDOMENEE.xml"/>
  <play id="fre001467" file="RADET-RABOTEAU_AVAREAMI.xml"/>
  <play id="fre001468" file="ROTROU_LAUREPERSECUTEE.xml"/>
  <play id="fre001469" file="SAINT-GLAS_BOUTSRIMES.xml"/>
  <play id="fre001470" file="SAND_FRANCOISLECHAMPI.xml"/>
  <play id="fre001471" file="BERNARDT_ANTOINETTE.xml"/>
  <play id="fre001472" file="BERNARDT_GARCONDEDIXHUITANS.xml"/>
  <play id="fre001473" file="BERNARDT_HOMMEALAMAISON.xml"/>
  <play id="fre001474" file="BERNARDT_MAISONDUCRIME.xml"/>
  <play id="fre001475" file="BERNARDT_OPERATIONMAGISTRALE.xml"/>
  <play id="fre001476" file="CHAPUZEAU_GENEVEDELIVREE.xml"/>
  <play id="fre001477" file="CORNEILLET_BARONDALBIKRAC.xml"/>
  <play id="fre001478" file="COURTELINE_ALLO.xml"/>
  <play id="fre001479" file="COURTELINE_ANIMAUXMALADESDELAFAIM.xml"/>
  <play id="fre001480" file="COURTELINE_ATELIER.xml"/>
  <play id="fre001481" file="COURTELINE_ECOLEDESMUFLES.xml"/>
  <play id="fre001482" file="COURTELINE_FERMETAMALLE.xml"/>
  <play id="fre001483" file="COURTELINE_GORA.xml"/>
  <play id="fre001484" file="COURTELINE_INCENDIE.xml"/>
  <play id="fre001485" file="COURTELINE_MOISDEPRISON.xml"/>
  <play id="fre001486" file="COURTELINE_OURS.xml"/>
  <play id="fre001487" file="COURTELINE_PANTHEONCOURCELLES.xml"/>
  <play id="fre001488" file="COURTELINE_PRINCIPALTEMOIN.xml"/>
  <play id="fre001489" file="COURTELINE_PRIXDUNEGIFLE.xml"/>
  <play id="fre001490" file="COURTELINE_QUELQUESLIVRES.xml"/>
  <play id="fre001491" file="COURTELINE_RUEDELAPOMPE.xml"/>
  <play id="fre001492" file="DIDEROT_ENTRETIENDELAMBERTDIDEROT.xml"/>
  <play id="fre001493" file="GONNET_ANGELIQUE.xml"/>
  <play id="fre001494" file="GONNET_CLEMENTINE.xml"/>
  <play id="fre001495" file="GONNET_EUGENIE.xml"/>
  <play id="fre001496" file="GONNET_EUPHEMIE.xml"/>
  <play id="fre001497" file="GONNET_JULIETTEOULADANSEUSE.xml"/>
  <play id="fre001498" file="GONNET_LISETTE.xml"/>
  <play id="fre001499" file="HAUTEROCHE_AMANTFLATTEPOINT.xml"/>
  <play id="fre001500" file="HAUTEROCHE_DEUIL.xml"/>
</ids>
